{
"meta":{"test_sets":[],"test_metrics":[],"learn_metrics":[{"best_value":"Min","name":"Logloss"}],"launch_mode":"Train","parameters":"","iteration_count":1000,"learn_sets":["learn"],"name":"experiment"},
"iterations":[
{"learn":[0.6894101212],"iteration":0,"passed_time":0.05875776003,"remaining_time":58.69900227},
{"learn":[0.6851130972],"iteration":1,"passed_time":0.09299479547,"remaining_time":46.40440294},
{"learn":[0.6812663447],"iteration":2,"passed_time":0.1158580284,"remaining_time":38.50348476},
{"learn":[0.6777168223],"iteration":3,"passed_time":0.1229853626,"remaining_time":30.62335528},
{"learn":[0.6740666193],"iteration":4,"passed_time":0.142485262,"remaining_time":28.35456714},
{"learn":[0.6703526315],"iteration":5,"passed_time":0.1653041448,"remaining_time":27.38538666},
{"learn":[0.6667080897],"iteration":6,"passed_time":0.1886676306,"remaining_time":26.76385102},
{"learn":[0.6628546468],"iteration":7,"passed_time":0.2140573114,"remaining_time":26.54310661},
{"learn":[0.6594703541],"iteration":8,"passed_time":0.2203064519,"remaining_time":24.25818821},
{"learn":[0.6559051299],"iteration":9,"passed_time":0.2442599549,"remaining_time":24.18173554},
{"learn":[0.6529114125],"iteration":10,"passed_time":0.247098812,"remaining_time":22.21642955},
{"learn":[0.6493557506],"iteration":11,"passed_time":0.2722791154,"remaining_time":22.41764717},
{"learn":[0.646236022],"iteration":12,"passed_time":0.2793979857,"remaining_time":21.21275476},
{"learn":[0.6427059153],"iteration":13,"passed_time":0.3017881411,"remaining_time":21.25450765},
{"learn":[0.6393640846],"iteration":14,"passed_time":0.3217863581,"remaining_time":21.13063752},
{"learn":[0.636018824],"iteration":15,"passed_time":0.3413583963,"remaining_time":20.99354137},
{"learn":[0.6330126329],"iteration":16,"passed_time":0.3669602395,"remaining_time":21.2189362},
{"learn":[0.6296116855],"iteration":17,"passed_time":0.3889542933,"remaining_time":21.21961756},
{"learn":[0.6264118215],"iteration":18,"passed_time":0.4136245288,"remaining_time":21.35608751},
{"learn":[0.6227528608],"iteration":19,"passed_time":0.4375154598,"remaining_time":21.43825753},
{"learn":[0.6196458583],"iteration":20,"passed_time":0.4583407217,"remaining_time":21.36740793},
{"learn":[0.6164639461],"iteration":21,"passed_time":0.4820973091,"remaining_time":21.43141674},
{"learn":[0.6132886738],"iteration":22,"passed_time":0.5046771161,"remaining_time":21.43780619},
{"learn":[0.6100962362],"iteration":23,"passed_time":0.5276067622,"remaining_time":21.45600833},
{"learn":[0.6074358276],"iteration":24,"passed_time":0.5503324907,"remaining_time":21.46296714},
{"learn":[0.6044498083],"iteration":25,"passed_time":0.5732189753,"remaining_time":21.47366469},
{"learn":[0.6019024425],"iteration":26,"passed_time":0.5865221967,"remaining_time":21.13652212},
{"learn":[0.5993917583],"iteration":27,"passed_time":0.6089454174,"remaining_time":21.1391052},
{"learn":[0.5968327115],"iteration":28,"passed_time":0.6331226841,"remaining_time":21.19869401},
{"learn":[0.5942403426],"iteration":29,"passed_time":0.6539521697,"remaining_time":21.14445349},
{"learn":[0.5909270788],"iteration":30,"passed_time":0.6801500861,"remaining_time":21.26017527},
{"learn":[0.5881604545],"iteration":31,"passed_time":0.7019006674,"remaining_time":21.23249519},
{"learn":[0.5858576844],"iteration":32,"passed_time":0.731836445,"remaining_time":21.44502552},
{"learn":[0.5833502712],"iteration":33,"passed_time":0.7542281938,"remaining_time":21.42895398},
{"learn":[0.5808468129],"iteration":34,"passed_time":0.7759011832,"remaining_time":21.39270405},
{"learn":[0.578460583],"iteration":35,"passed_time":0.7975124484,"remaining_time":21.35561112},
{"learn":[0.5760486506],"iteration":36,"passed_time":0.8196152202,"remaining_time":21.33214749},
{"learn":[0.5738089332],"iteration":37,"passed_time":0.8454464924,"remaining_time":21.40314541},
{"learn":[0.5714557424],"iteration":38,"passed_time":0.8703024693,"remaining_time":21.44514546},
{"learn":[0.5688882753],"iteration":39,"passed_time":0.8914535312,"remaining_time":21.39488475},
{"learn":[0.5666291449],"iteration":40,"passed_time":0.9161019505,"remaining_time":21.42784806},
{"learn":[0.5647216973],"iteration":41,"passed_time":0.9390026851,"remaining_time":21.4182041},
{"learn":[0.5625161161],"iteration":42,"passed_time":0.9694720873,"remaining_time":21.57639041},
{"learn":[0.5600591969],"iteration":43,"passed_time":0.9962335317,"remaining_time":21.64543764},
{"learn":[0.5572419436],"iteration":44,"passed_time":1.019402938,"remaining_time":21.63399569},
{"learn":[0.5554504407],"iteration":45,"passed_time":1.045491453,"remaining_time":21.68258362},
{"learn":[0.5531837688],"iteration":46,"passed_time":1.068117617,"remaining_time":21.65778913},
{"learn":[0.5508327399],"iteration":47,"passed_time":1.08877121,"remaining_time":21.59396233},
{"learn":[0.5492628463],"iteration":48,"passed_time":1.092851719,"remaining_time":21.21024459},
{"learn":[0.5474197963],"iteration":49,"passed_time":1.118860155,"remaining_time":21.25834295},
{"learn":[0.5450254312],"iteration":50,"passed_time":1.144084742,"remaining_time":21.28894941},
{"learn":[0.542521296],"iteration":51,"passed_time":1.171642598,"remaining_time":21.35994582},
{"learn":[0.5400184685],"iteration":52,"passed_time":1.206280597,"remaining_time":21.55373067},
{"learn":[0.5382242947],"iteration":53,"passed_time":1.23340527,"remaining_time":21.60743307},
{"learn":[0.5361582604],"iteration":54,"passed_time":1.26505659,"remaining_time":21.73597233},
{"learn":[0.5341671504],"iteration":55,"passed_time":1.3110773,"remaining_time":22.10101734},
{"learn":[0.5324820104],"iteration":56,"passed_time":1.336937668,"remaining_time":22.11810913},
{"learn":[0.5306052914],"iteration":57,"passed_time":1.370798105,"remaining_time":22.26365198},
{"learn":[0.5288353096],"iteration":58,"passed_time":1.395679732,"remaining_time":22.25990895},
{"learn":[0.5265175714],"iteration":59,"passed_time":1.416476395,"remaining_time":22.19146352},
{"learn":[0.5248159733],"iteration":60,"passed_time":1.440633179,"remaining_time":22.17630418},
{"learn":[0.523055689],"iteration":61,"passed_time":1.467532052,"remaining_time":22.20233976},
{"learn":[0.5214314917],"iteration":62,"passed_time":1.49167737,"remaining_time":22.18574121},
{"learn":[0.5197707789],"iteration":63,"passed_time":1.51671945,"remaining_time":22.18202196},
{"learn":[0.5183601708],"iteration":64,"passed_time":1.544743247,"remaining_time":22.22053748},
{"learn":[0.5167285579],"iteration":65,"passed_time":1.566363123,"remaining_time":22.16641147},
{"learn":[0.5149643919],"iteration":66,"passed_time":1.590565509,"remaining_time":22.14921821},
{"learn":[0.5128450377],"iteration":67,"passed_time":1.610974452,"remaining_time":22.07982632},
{"learn":[0.5112829604],"iteration":68,"passed_time":1.638295693,"remaining_time":22.10512015},
{"learn":[0.5094195039],"iteration":69,"passed_time":1.66826841,"remaining_time":22.16413744},
{"learn":[0.5077619505],"iteration":70,"passed_time":1.693724318,"remaining_time":22.16154776},
{"learn":[0.5058391984],"iteration":71,"passed_time":1.715840006,"remaining_time":22.11527119},
{"learn":[0.5043550312],"iteration":72,"passed_time":1.737297096,"remaining_time":22.06129326},
{"learn":[0.502617603],"iteration":73,"passed_time":1.762659135,"remaining_time":22.0570589},
{"learn":[0.5012086269],"iteration":74,"passed_time":1.787587253,"remaining_time":22.04690946},
{"learn":[0.4997092829],"iteration":75,"passed_time":1.809599376,"remaining_time":22.00091873},
{"learn":[0.4985268677],"iteration":76,"passed_time":1.833764773,"remaining_time":21.98136215},
{"learn":[0.4968074927],"iteration":77,"passed_time":1.86026193,"remaining_time":21.98924999},
{"learn":[0.4951846897],"iteration":78,"passed_time":1.880776069,"remaining_time":21.92651594},
{"learn":[0.4933347056],"iteration":79,"passed_time":1.903302418,"remaining_time":21.8879778},
{"learn":[0.491350415],"iteration":80,"passed_time":1.92491395,"remaining_time":21.83945581},
{"learn":[0.4901624288],"iteration":81,"passed_time":1.930800237,"remaining_time":21.61554411},
{"learn":[0.4888658416],"iteration":82,"passed_time":1.959940337,"remaining_time":21.65379866},
{"learn":[0.4872687145],"iteration":83,"passed_time":1.98200688,"remaining_time":21.61331312},
{"learn":[0.4859748416],"iteration":84,"passed_time":2.01229363,"remaining_time":21.66174908},
{"learn":[0.4847028257],"iteration":85,"passed_time":2.037619251,"remaining_time":21.65562786},
{"learn":[0.4832451517],"iteration":86,"passed_time":2.060448654,"remaining_time":21.62286921},
{"learn":[0.4820204602],"iteration":87,"passed_time":2.081846596,"remaining_time":21.57550109},
{"learn":[0.4807747342],"iteration":88,"passed_time":2.106870294,"remaining_time":21.56582964},
{"learn":[0.4792109474],"iteration":89,"passed_time":2.127311649,"remaining_time":21.50948445},
{"learn":[0.4781928872],"iteration":90,"passed_time":2.152261483,"remaining_time":21.4989636},
{"learn":[0.4768636204],"iteration":91,"passed_time":2.174861119,"remaining_time":21.46493366},
{"learn":[0.475295034],"iteration":92,"passed_time":2.197047487,"remaining_time":21.42711904},
{"learn":[0.4740154924],"iteration":93,"passed_time":2.217358929,"remaining_time":21.37156585},
{"learn":[0.4729274648],"iteration":94,"passed_time":2.24029257,"remaining_time":21.34173448},
{"learn":[0.471847703],"iteration":95,"passed_time":2.264671714,"remaining_time":21.32565864},
{"learn":[0.4706812321],"iteration":96,"passed_time":2.290739171,"remaining_time":21.32512858},
{"learn":[0.4698174784],"iteration":97,"passed_time":2.314210159,"remaining_time":21.30017922},
{"learn":[0.468763748],"iteration":98,"passed_time":2.335734689,"remaining_time":21.257545},
{"learn":[0.4676242865],"iteration":99,"passed_time":2.359887852,"remaining_time":21.23899067},
{"learn":[0.466240991],"iteration":100,"passed_time":2.382524603,"remaining_time":21.20682791},
{"learn":[0.4652142463],"iteration":101,"passed_time":2.401947828,"remaining_time":21.14656029},
{"learn":[0.464226577],"iteration":102,"passed_time":2.425151123,"remaining_time":21.12000541},
{"learn":[0.4628608436],"iteration":103,"passed_time":2.446999438,"remaining_time":21.08184131},
{"learn":[0.4619210733],"iteration":104,"passed_time":2.473238971,"remaining_time":21.0814179},
{"learn":[0.4607438377],"iteration":105,"passed_time":2.49500415,"remaining_time":21.04277085},
{"learn":[0.4596689492],"iteration":106,"passed_time":2.517629032,"remaining_time":21.01161426},
{"learn":[0.4584686829],"iteration":107,"passed_time":2.539845001,"remaining_time":20.97723834},
{"learn":[0.457187853],"iteration":108,"passed_time":2.560481053,"remaining_time":20.93017081},
{"learn":[0.4555673333],"iteration":109,"passed_time":2.584416215,"remaining_time":20.91027665},
{"learn":[0.4546828517],"iteration":110,"passed_time":2.608892815,"remaining_time":20.89464606},
{"learn":[0.4536710325],"iteration":111,"passed_time":2.642708506,"remaining_time":20.95290315},
{"learn":[0.4526664703],"iteration":112,"passed_time":2.668727811,"remaining_time":20.94833246},
{"learn":[0.4518429797],"iteration":113,"passed_time":2.690790884,"remaining_time":20.91263792},
{"learn":[0.4511004275],"iteration":114,"passed_time":2.711292504,"remaining_time":20.86516405},
{"learn":[0.4503614513],"iteration":115,"passed_time":2.735010504,"remaining_time":20.84266626},
{"learn":[0.4496098788],"iteration":116,"passed_time":2.748542254,"remaining_time":20.74327188},
{"learn":[0.448481063],"iteration":117,"passed_time":2.770992308,"remaining_time":20.71199336},
{"learn":[0.4471908814],"iteration":118,"passed_time":2.794948944,"remaining_time":20.69201697},
{"learn":[0.4459198784],"iteration":119,"passed_time":2.817737865,"remaining_time":20.66341101},
{"learn":[0.4450481891],"iteration":120,"passed_time":2.840708221,"remaining_time":20.63621923},
{"learn":[0.444192219],"iteration":121,"passed_time":2.863953983,"remaining_time":20.61107866},
{"learn":[0.4434319437],"iteration":122,"passed_time":2.886415835,"remaining_time":20.58037957},
{"learn":[0.442437341],"iteration":123,"passed_time":2.909624039,"remaining_time":20.55508595},
{"learn":[0.4412463546],"iteration":124,"passed_time":2.937654737,"remaining_time":20.56358316},
{"learn":[0.4404861126],"iteration":125,"passed_time":2.958405685,"remaining_time":20.52100451},
{"learn":[0.4396124905],"iteration":126,"passed_time":2.983397188,"remaining_time":20.50791925},
{"learn":[0.4386047412],"iteration":127,"passed_time":3.003841458,"remaining_time":20.46366993},
{"learn":[0.4379602047],"iteration":128,"passed_time":3.025882926,"remaining_time":20.43057386},
{"learn":[0.437061473],"iteration":129,"passed_time":3.051787878,"remaining_time":20.42350349},
{"learn":[0.4360952175],"iteration":130,"passed_time":3.072404751,"remaining_time":20.38106663},
{"learn":[0.4353325485],"iteration":131,"passed_time":3.09545676,"remaining_time":20.35497324},
{"learn":[0.4346820897],"iteration":132,"passed_time":3.116483508,"remaining_time":20.31572332},
{"learn":[0.433907453],"iteration":133,"passed_time":3.140677627,"remaining_time":20.29721511},
{"learn":[0.4330165663],"iteration":134,"passed_time":3.162160673,"remaining_time":20.26125172},
{"learn":[0.4320891063],"iteration":135,"passed_time":3.185189167,"remaining_time":20.23531942},
{"learn":[0.431288792],"iteration":136,"passed_time":3.20579871,"remaining_time":20.19419187},
{"learn":[0.4304664598],"iteration":137,"passed_time":3.234172313,"remaining_time":20.20185894},
{"learn":[0.4298267964],"iteration":138,"passed_time":3.261077522,"remaining_time":20.19991184},
{"learn":[0.4291120676],"iteration":139,"passed_time":3.289347977,"remaining_time":20.20599472},
{"learn":[0.427718773],"iteration":140,"passed_time":3.312785605,"remaining_time":20.18214776},
{"learn":[0.4270538393],"iteration":141,"passed_time":3.335246302,"remaining_time":20.15240371},
{"learn":[0.426418898],"iteration":142,"passed_time":3.356069621,"remaining_time":20.11294871},
{"learn":[0.4257159027],"iteration":143,"passed_time":3.380327979,"remaining_time":20.09417188},
{"learn":[0.4249940137],"iteration":144,"passed_time":3.40025902,"remaining_time":20.04980319},
{"learn":[0.4243996167],"iteration":145,"passed_time":3.424122636,"remaining_time":20.02877213},
{"learn":[0.4235376063],"iteration":146,"passed_time":3.447929874,"remaining_time":20.00737539},
{"learn":[0.4225290423],"iteration":147,"passed_time":3.470825855,"remaining_time":19.98070019},
{"learn":[0.4217297498],"iteration":148,"passed_time":3.493352408,"remaining_time":19.95196577},
{"learn":[0.4211376839],"iteration":149,"passed_time":3.513862978,"remaining_time":19.91189021},
{"learn":[0.4201966292],"iteration":150,"passed_time":3.53563872,"remaining_time":19.87918724},
{"learn":[0.4191805549],"iteration":151,"passed_time":3.558104369,"remaining_time":19.85047701},
{"learn":[0.4185322303],"iteration":152,"passed_time":3.583080688,"remaining_time":19.83574734},
{"learn":[0.4177340844],"iteration":153,"passed_time":3.603075192,"remaining_time":19.79351696},
{"learn":[0.4167658311],"iteration":154,"passed_time":3.628235624,"remaining_time":19.77973614},
{"learn":[0.4160848926],"iteration":155,"passed_time":3.650590935,"remaining_time":19.75063301},
{"learn":[0.4154301185],"iteration":156,"passed_time":3.670797692,"remaining_time":19.71007933},
{"learn":[0.4145302894],"iteration":157,"passed_time":3.695277861,"remaining_time":19.6925567},
{"learn":[0.4139522773],"iteration":158,"passed_time":3.71572663,"remaining_time":19.65362325},
{"learn":[0.4130502008],"iteration":159,"passed_time":3.739650975,"remaining_time":19.63316762},
{"learn":[0.412552865],"iteration":160,"passed_time":3.761424132,"remaining_time":19.60145868},
{"learn":[0.4116124039],"iteration":161,"passed_time":3.782765257,"remaining_time":19.56763756},
{"learn":[0.4106182779],"iteration":162,"passed_time":3.803457938,"remaining_time":19.53063984},
{"learn":[0.4099462404],"iteration":163,"passed_time":3.828539621,"remaining_time":19.51621417},
{"learn":[0.409341236],"iteration":164,"passed_time":3.857030661,"remaining_time":19.51891274},
{"learn":[0.4087403719],"iteration":165,"passed_time":3.8807605,"remaining_time":19.4973148},
{"learn":[0.4080845965],"iteration":166,"passed_time":3.911374665,"remaining_time":19.51003052},
{"learn":[0.407450761],"iteration":167,"passed_time":3.934470341,"remaining_time":19.48499598},
{"learn":[0.4067860212],"iteration":168,"passed_time":3.9564866,"remaining_time":19.45467671},
{"learn":[0.4063604123],"iteration":169,"passed_time":3.979044617,"remaining_time":19.42710019},
{"learn":[0.4058098289],"iteration":170,"passed_time":3.99923194,"remaining_time":19.38808935},
{"learn":[0.4052201002],"iteration":171,"passed_time":4.023366835,"remaining_time":19.36830081},
{"learn":[0.404724705],"iteration":172,"passed_time":4.048083305,"remaining_time":19.35124216},
{"learn":[0.4039233105],"iteration":173,"passed_time":4.069628931,"remaining_time":19.31904309},
{"learn":[0.4034394387],"iteration":174,"passed_time":4.09416921,"remaining_time":19.30108342},
{"learn":[0.4022928509],"iteration":175,"passed_time":4.114254024,"remaining_time":19.26218929},
{"learn":[0.4017552858],"iteration":176,"passed_time":4.136438476,"remaining_time":19.23327043},
{"learn":[0.4011300904],"iteration":177,"passed_time":4.157922298,"remaining_time":19.20119174},
{"learn":[0.4003789624],"iteration":178,"passed_time":4.180847165,"remaining_time":19.17584091},
{"learn":[0.3999187716],"iteration":179,"passed_time":4.200640713,"remaining_time":19.13625214},
{"learn":[0.3991728852],"iteration":180,"passed_time":4.227851274,"remaining_time":19.13044306},
{"learn":[0.3986949785],"iteration":181,"passed_time":4.253276884,"remaining_time":19.11637632},
{"learn":[0.3983423373],"iteration":182,"passed_time":4.275195895,"remaining_time":19.08653031},
{"learn":[0.3977603309],"iteration":183,"passed_time":4.298013486,"remaining_time":19.06075546},
{"learn":[0.3971135753],"iteration":184,"passed_time":4.318774247,"remaining_time":19.02595141},
{"learn":[0.3963180191],"iteration":185,"passed_time":4.345480431,"remaining_time":19.01731759},
{"learn":[0.3957789343],"iteration":186,"passed_time":4.367985499,"remaining_time":18.99022572},
{"learn":[0.3949180353],"iteration":187,"passed_time":4.389859174,"remaining_time":18.96045558},
{"learn":[0.3945006418],"iteration":188,"passed_time":4.414506161,"remaining_time":18.9426693},
{"learn":[0.3939641616],"iteration":189,"passed_time":4.435195634,"remaining_time":18.90793928},
{"learn":[0.3934421126],"iteration":190,"passed_time":4.459571669,"remaining_time":18.8889711},
{"learn":[0.3929897788],"iteration":191,"passed_time":4.481791393,"remaining_time":18.86087211},
{"learn":[0.3924943554],"iteration":192,"passed_time":4.5072463,"remaining_time":18.84636147},
{"learn":[0.392205392],"iteration":193,"passed_time":4.53742549,"remaining_time":18.8513657},
{"learn":[0.3915735494],"iteration":194,"passed_time":4.561027175,"remaining_time":18.82885577},
{"learn":[0.3910543518],"iteration":195,"passed_time":4.583637551,"remaining_time":18.80226832},
{"learn":[0.3906629036],"iteration":196,"passed_time":4.604809682,"remaining_time":18.76985876},
{"learn":[0.3899406962],"iteration":197,"passed_time":4.627427644,"remaining_time":18.74341904},
{"learn":[0.3894628168],"iteration":198,"passed_time":4.651860392,"remaining_time":18.72432248},
{"learn":[0.3884210584],"iteration":199,"passed_time":4.673811683,"remaining_time":18.69524673},
{"learn":[0.3878284613],"iteration":200,"passed_time":4.696245943,"remaining_time":18.66816173},
{"learn":[0.3870509196],"iteration":201,"passed_time":4.716219246,"remaining_time":18.63140078},
{"learn":[0.3865102942],"iteration":202,"passed_time":4.741067133,"remaining_time":18.61394337},
{"learn":[0.3858506398],"iteration":203,"passed_time":4.763688177,"remaining_time":18.58772446},
{"learn":[0.3853242013],"iteration":204,"passed_time":4.783700427,"remaining_time":18.55142361},
{"learn":[0.3847959282],"iteration":205,"passed_time":4.809184174,"remaining_time":18.53637007},
{"learn":[0.384302845],"iteration":206,"passed_time":4.829769015,"remaining_time":18.50244845},
{"learn":[0.3835654986],"iteration":207,"passed_time":4.858053539,"remaining_time":18.49797309},
{"learn":[0.3831288683],"iteration":208,"passed_time":4.880085884,"remaining_time":18.46960734},
{"learn":[0.3822110929],"iteration":209,"passed_time":4.903167529,"remaining_time":18.44524927},
{"learn":[0.3814816384],"iteration":210,"passed_time":4.925416624,"remaining_time":18.41779013},
{"learn":[0.3808374837],"iteration":211,"passed_time":4.946539318,"remaining_time":18.38619332},
{"learn":[0.3804818151],"iteration":212,"passed_time":4.96944787,"remaining_time":18.3612933},
{"learn":[0.3798005775],"iteration":213,"passed_time":4.991319018,"remaining_time":18.33260163},
{"learn":[0.3794209177],"iteration":214,"passed_time":5.014035155,"remaining_time":18.30705859},
{"learn":[0.3790035897],"iteration":215,"passed_time":5.037346519,"remaining_time":18.28370218},
{"learn":[0.3784195173],"iteration":216,"passed_time":5.060072984,"remaining_time":18.2582357},
{"learn":[0.3779117482],"iteration":217,"passed_time":5.081781049,"remaining_time":18.2291412},
{"learn":[0.3773814994],"iteration":218,"passed_time":5.104061627,"remaining_time":18.20215585},
{"learn":[0.376965831],"iteration":219,"passed_time":5.12992475,"remaining_time":18.18791502},
{"learn":[0.3762707855],"iteration":220,"passed_time":5.151136699,"remaining_time":18.15717416},
{"learn":[0.3758736111],"iteration":221,"passed_time":5.182326674,"remaining_time":18.16148717},
{"learn":[0.3751505957],"iteration":222,"passed_time":5.207367196,"remaining_time":18.14405521},
{"learn":[0.3747195748],"iteration":223,"passed_time":5.228286765,"remaining_time":18.11227915},
{"learn":[0.3743331734],"iteration":224,"passed_time":5.253265103,"remaining_time":18.0945798},
{"learn":[0.3736860571],"iteration":225,"passed_time":5.275713022,"remaining_time":18.06814991},
{"learn":[0.3733113833],"iteration":226,"passed_time":5.29751745,"remaining_time":18.03956383},
{"learn":[0.3728931613],"iteration":227,"passed_time":5.318868085,"remaining_time":18.00950071},
{"learn":[0.3724624399],"iteration":228,"passed_time":5.341996133,"remaining_time":17.9854979},
{"learn":[0.3717891109],"iteration":229,"passed_time":5.364243209,"remaining_time":17.95855335},
{"learn":[0.3713358711],"iteration":230,"passed_time":5.385366384,"remaining_time":17.92790801},
{"learn":[0.3709591013],"iteration":231,"passed_time":5.408027159,"remaining_time":17.90243473},
{"learn":[0.3705633735],"iteration":232,"passed_time":5.42891251,"remaining_time":17.87114118},
{"learn":[0.3698770519],"iteration":233,"passed_time":5.455774131,"remaining_time":17.85949993},
{"learn":[0.3694401923],"iteration":234,"passed_time":5.477446113,"remaining_time":17.83083522},
{"learn":[0.3690622568],"iteration":235,"passed_time":5.502703309,"remaining_time":17.81383614},
{"learn":[0.3685673275],"iteration":236,"passed_time":5.52746136,"remaining_time":17.79516041},
{"learn":[0.3682008837],"iteration":237,"passed_time":5.549100579,"remaining_time":17.76644807},
{"learn":[0.3679256692],"iteration":238,"passed_time":5.570051579,"remaining_time":17.73560356},
{"learn":[0.3676047715],"iteration":239,"passed_time":5.590680109,"remaining_time":17.70382035},
{"learn":[0.3672754508],"iteration":240,"passed_time":5.617081954,"remaining_time":17.69031205},
{"learn":[0.3669019448],"iteration":241,"passed_time":5.64210294,"remaining_time":17.67237202},
{"learn":[0.3663539681],"iteration":242,"passed_time":5.663885695,"remaining_time":17.64428589},
{"learn":[0.3657414943],"iteration":243,"passed_time":5.687436066,"remaining_time":17.62172814},
{"learn":[0.3653967064],"iteration":244,"passed_time":5.707322162,"remaining_time":17.58787034},
{"learn":[0.3647431458],"iteration":245,"passed_time":5.730984563,"remaining_time":17.56570065},
{"learn":[0.3639863983],"iteration":246,"passed_time":5.753099859,"remaining_time":17.5388024},
{"learn":[0.3633042415],"iteration":247,"passed_time":5.776866826,"remaining_time":17.51695102},
{"learn":[0.3629557156],"iteration":248,"passed_time":5.799971388,"remaining_time":17.49308639},
{"learn":[0.3626230143],"iteration":249,"passed_time":5.833194061,"remaining_time":17.49958218},
{"learn":[0.3622025424],"iteration":250,"passed_time":5.853472437,"remaining_time":17.46713488},
{"learn":[0.3616027957],"iteration":251,"passed_time":5.874964066,"remaining_time":17.4383854},
{"learn":[0.361211017],"iteration":252,"passed_time":5.899466236,"remaining_time":17.41858213},
{"learn":[0.3608645624],"iteration":253,"passed_time":5.92366735,"remaining_time":17.39785765},
{"learn":[0.3602261062],"iteration":254,"passed_time":5.945958518,"remaining_time":17.37152587},
{"learn":[0.3593462949],"iteration":255,"passed_time":5.969581308,"remaining_time":17.34909568},
{"learn":[0.3591260089],"iteration":256,"passed_time":5.989849785,"remaining_time":17.31695872},
{"learn":[0.3585406165],"iteration":257,"passed_time":6.013822994,"remaining_time":17.29556845},
{"learn":[0.3581023268],"iteration":258,"passed_time":6.03950083,"remaining_time":17.27903519},
{"learn":[0.3577133792],"iteration":259,"passed_time":6.060649283,"remaining_time":17.24954027},
{"learn":[0.3570363844],"iteration":260,"passed_time":6.087079562,"remaining_time":17.23506435},
{"learn":[0.3567503319],"iteration":261,"passed_time":6.107536692,"remaining_time":17.20367206},
{"learn":[0.3563005763],"iteration":262,"passed_time":6.132551808,"remaining_time":17.18513567},
{"learn":[0.3560250455],"iteration":263,"passed_time":6.154999271,"remaining_time":17.15939191},
{"learn":[0.355522623],"iteration":264,"passed_time":6.17607326,"remaining_time":17.12986357},
{"learn":[0.3550675068],"iteration":265,"passed_time":6.201494886,"remaining_time":17.11239566},
{"learn":[0.3546731397],"iteration":266,"passed_time":6.222621605,"remaining_time":17.08307729},
{"learn":[0.354339695],"iteration":267,"passed_time":6.24983821,"remaining_time":17.07045362},
{"learn":[0.3536355513],"iteration":268,"passed_time":6.272094618,"remaining_time":17.04424225},
{"learn":[0.3531089526],"iteration":269,"passed_time":6.295181439,"remaining_time":17.02030537},
{"learn":[0.3525987532],"iteration":270,"passed_time":6.317629004,"remaining_time":16.99465514},
{"learn":[0.3520431909],"iteration":271,"passed_time":6.338696518,"remaining_time":16.9653348},
{"learn":[0.3518095107],"iteration":272,"passed_time":6.36183849,"remaining_time":16.9415992},
{"learn":[0.3512473504],"iteration":273,"passed_time":6.38966625,"remaining_time":16.93028357},
{"learn":[0.350913074],"iteration":274,"passed_time":6.420309528,"remaining_time":16.92627057},
{"learn":[0.3507451508],"iteration":275,"passed_time":6.460863173,"remaining_time":16.94806137},
{"learn":[0.3504092337],"iteration":276,"passed_time":6.487633351,"remaining_time":16.93342568},
{"learn":[0.3500928561],"iteration":277,"passed_time":6.514251035,"remaining_time":16.91830665},
{"learn":[0.3497418577],"iteration":278,"passed_time":6.541449924,"remaining_time":16.90460715},
{"learn":[0.349315985],"iteration":279,"passed_time":6.577495933,"remaining_time":16.91356097},
{"learn":[0.3490128945],"iteration":280,"passed_time":6.609898037,"remaining_time":16.91287078},
{"learn":[0.3484147728],"iteration":281,"passed_time":6.650681078,"remaining_time":16.93329438},
{"learn":[0.3481069314],"iteration":282,"passed_time":6.688857616,"remaining_time":16.94668166},
{"learn":[0.3476120826],"iteration":283,"passed_time":6.724826728,"remaining_time":16.95414062},
{"learn":[0.3474127438],"iteration":284,"passed_time":6.75511032,"remaining_time":16.94703115},
{"learn":[0.3469296311],"iteration":285,"passed_time":6.783556069,"remaining_time":16.93517144},
{"learn":[0.3465344334],"iteration":286,"passed_time":6.810115489,"remaining_time":16.91850991},
{"learn":[0.3462601922],"iteration":287,"passed_time":6.834431038,"remaining_time":16.89623229},
{"learn":[0.3458536112],"iteration":288,"passed_time":6.864989171,"remaining_time":16.88929862},
{"learn":[0.3455124047],"iteration":289,"passed_time":6.902292652,"remaining_time":16.89871649},
{"learn":[0.3451862659],"iteration":290,"passed_time":6.948020496,"remaining_time":16.9283386},
{"learn":[0.3448387359],"iteration":291,"passed_time":6.982821034,"remaining_time":16.93094963},
{"learn":[0.3443138704],"iteration":292,"passed_time":7.033766127,"remaining_time":16.97226161},
{"learn":[0.3440629833],"iteration":293,"passed_time":7.069471641,"remaining_time":16.97635027},
{"learn":[0.3434663061],"iteration":294,"passed_time":7.104268638,"remaining_time":16.97799793},
{"learn":[0.3429026067],"iteration":295,"passed_time":7.145423264,"remaining_time":16.9945202},
{"learn":[0.3425957963],"iteration":296,"passed_time":7.168895199,"remaining_time":16.96879907},
{"learn":[0.342026037],"iteration":297,"passed_time":7.191843821,"remaining_time":16.94186028},
{"learn":[0.3414237253],"iteration":298,"passed_time":7.214780088,"remaining_time":16.9149192},
{"learn":[0.3410624602],"iteration":299,"passed_time":7.241392124,"remaining_time":16.89658162},
{"learn":[0.3407446531],"iteration":300,"passed_time":7.268913772,"remaining_time":16.88030142},
{"learn":[0.3404914911],"iteration":301,"passed_time":7.293872337,"remaining_time":16.85802282},
{"learn":[0.3400274738],"iteration":302,"passed_time":7.317912556,"remaining_time":16.83361403},
{"learn":[0.3397318374],"iteration":303,"passed_time":7.342180569,"remaining_time":16.8097292},
{"learn":[0.339250925],"iteration":304,"passed_time":7.364369232,"remaining_time":16.78110366},
{"learn":[0.3390307781],"iteration":305,"passed_time":7.392554018,"remaining_time":16.76611924},
{"learn":[0.3386387894],"iteration":306,"passed_time":7.419180859,"remaining_time":16.74753204},
{"learn":[0.3384288981],"iteration":307,"passed_time":7.451790711,"remaining_time":16.74233497},
{"learn":[0.3381882809],"iteration":308,"passed_time":7.486045052,"remaining_time":16.74063796},
{"learn":[0.3378472633],"iteration":309,"passed_time":7.512704474,"remaining_time":16.72182609},
{"learn":[0.3375007355],"iteration":310,"passed_time":7.546396003,"remaining_time":16.71854291},
{"learn":[0.3371077833],"iteration":311,"passed_time":7.570053818,"remaining_time":16.69293919},
{"learn":[0.3366276836],"iteration":312,"passed_time":7.593507936,"remaining_time":16.6669008},
{"learn":[0.336188793],"iteration":313,"passed_time":7.614720312,"remaining_time":16.63598132},
{"learn":[0.3356727439],"iteration":314,"passed_time":7.638644907,"remaining_time":16.61102146},
{"learn":[0.3353731964],"iteration":315,"passed_time":7.664573744,"remaining_time":16.59040646},
{"learn":[0.3351076426],"iteration":316,"passed_time":7.688684002,"remaining_time":16.56583966},
{"learn":[0.3349026278],"iteration":317,"passed_time":7.71108471,"remaining_time":16.53760935},
{"learn":[0.3343463558],"iteration":318,"passed_time":7.734626899,"remaining_time":16.51185241},
{"learn":[0.3341716272],"iteration":319,"passed_time":7.767592536,"remaining_time":16.50613414},
{"learn":[0.3337036193],"iteration":320,"passed_time":7.790131413,"remaining_time":16.47819075},
{"learn":[0.333205667],"iteration":321,"passed_time":7.814190575,"remaining_time":16.45348202},
{"learn":[0.3329080043],"iteration":322,"passed_time":7.837417382,"remaining_time":16.42703272},
{"learn":[0.332514802],"iteration":323,"passed_time":7.861978973,"remaining_time":16.40338823},
{"learn":[0.3323465718],"iteration":324,"passed_time":7.887755555,"remaining_time":16.38226154},
{"learn":[0.3320719107],"iteration":325,"passed_time":7.911110848,"remaining_time":16.35610034},
{"learn":[0.3315330475],"iteration":326,"passed_time":7.938091074,"remaining_time":16.3374168},
{"learn":[0.3311743273],"iteration":327,"passed_time":7.97101086,"remaining_time":16.33085152},
{"learn":[0.3307741128],"iteration":328,"passed_time":7.995930273,"remaining_time":16.30780916},
{"learn":[0.3301316098],"iteration":329,"passed_time":8.026364213,"remaining_time":16.29595158},
{"learn":[0.3297377621],"iteration":330,"passed_time":8.060512323,"remaining_time":16.29148865},
{"learn":[0.3293988304],"iteration":331,"passed_time":8.088393475,"remaining_time":16.27423747},
{"learn":[0.3292206081],"iteration":332,"passed_time":8.113915194,"remaining_time":16.2521965},
{"learn":[0.3286516897],"iteration":333,"passed_time":8.143785725,"remaining_time":16.23880627},
{"learn":[0.3282935159],"iteration":334,"passed_time":8.172755544,"remaining_time":16.22352966},
{"learn":[0.3277972077],"iteration":335,"passed_time":8.205887272,"remaining_time":16.21639628},
{"learn":[0.3274173119],"iteration":336,"passed_time":8.240775632,"remaining_time":16.21256452},
{"learn":[0.3271557861],"iteration":337,"passed_time":8.272370916,"remaining_time":16.20209925},
{"learn":[0.3267856401],"iteration":338,"passed_time":8.296834126,"remaining_time":16.17760282},
{"learn":[0.3263818731],"iteration":339,"passed_time":8.326781738,"remaining_time":16.16375279},
{"learn":[0.3257754957],"iteration":340,"passed_time":8.361604132,"remaining_time":16.1592291},
{"learn":[0.3256615543],"iteration":341,"passed_time":8.394372435,"remaining_time":16.15057621},
{"learn":[0.3253901071],"iteration":342,"passed_time":8.436793525,"remaining_time":16.16027215},
{"learn":[0.3250469721],"iteration":343,"passed_time":8.463199603,"remaining_time":16.13912482},
{"learn":[0.3247891326],"iteration":344,"passed_time":8.491692653,"remaining_time":16.12190924},
{"learn":[0.3246209028],"iteration":345,"passed_time":8.523960035,"remaining_time":16.11176261},
{"learn":[0.3241100112],"iteration":346,"passed_time":8.556398929,"remaining_time":16.10181124},
{"learn":[0.3235913635],"iteration":347,"passed_time":8.585759047,"remaining_time":16.08596235},
{"learn":[0.323438857],"iteration":348,"passed_time":8.610994487,"remaining_time":16.06234215},
{"learn":[0.3231568684],"iteration":349,"passed_time":8.640054622,"remaining_time":16.04581573},
{"learn":[0.3226506634],"iteration":350,"passed_time":8.670602463,"remaining_time":16.03196866},
{"learn":[0.322453662],"iteration":351,"passed_time":8.693573074,"remaining_time":16.0040777},
{"learn":[0.3218699635],"iteration":352,"passed_time":8.723389054,"remaining_time":15.98876124},
{"learn":[0.3214167147],"iteration":353,"passed_time":8.752074527,"remaining_time":15.97129984},
{"learn":[0.3210982957],"iteration":354,"passed_time":8.776410267,"remaining_time":15.94587217},
{"learn":[0.3206054116],"iteration":355,"passed_time":8.804584315,"remaining_time":15.9273941},
{"learn":[0.3202387484],"iteration":356,"passed_time":8.833506492,"remaining_time":15.91020917},
{"learn":[0.3198175537],"iteration":357,"passed_time":8.860315733,"remaining_time":15.88916956},
{"learn":[0.3191179612],"iteration":358,"passed_time":8.889426279,"remaining_time":15.87220681},
{"learn":[0.3188262457],"iteration":359,"passed_time":8.917222443,"remaining_time":15.8528399},
{"learn":[0.3185435369],"iteration":360,"passed_time":8.945724772,"remaining_time":15.83467626},
{"learn":[0.3182876736],"iteration":361,"passed_time":8.972112791,"remaining_time":15.81272917},
{"learn":[0.3179909638],"iteration":362,"passed_time":9.006941886,"remaining_time":15.8055702},
{"learn":[0.3175826614],"iteration":363,"passed_time":9.052215134,"remaining_time":15.81650776},
{"learn":[0.3174110779],"iteration":364,"passed_time":9.076586665,"remaining_time":15.79077406},
{"learn":[0.3171457014],"iteration":365,"passed_time":9.105866303,"remaining_time":15.77354982},
{"learn":[0.3167586286],"iteration":366,"passed_time":9.136294374,"remaining_time":15.7582407},
{"learn":[0.3166628858],"iteration":367,"passed_time":9.172301507,"remaining_time":15.75243085},
{"learn":[0.3163565758],"iteration":368,"passed_time":9.2053107,"remaining_time":15.74133076},
{"learn":[0.3160802811],"iteration":369,"passed_time":9.2287803,"remaining_time":15.71386916},
{"learn":[0.3154400526],"iteration":370,"passed_time":9.247945355,"remaining_time":15.67913107},
{"learn":[0.3150968724],"iteration":371,"passed_time":9.269449008,"remaining_time":15.64842467},
{"learn":[0.3147451443],"iteration":372,"passed_time":9.289839982,"remaining_time":15.61589724},
{"learn":[0.314475613],"iteration":373,"passed_time":9.311141376,"remaining_time":15.58495856},
{"learn":[0.3142593542],"iteration":374,"passed_time":9.334120653,"remaining_time":15.55686776},
{"learn":[0.3141083577],"iteration":375,"passed_time":9.358315207,"remaining_time":15.53082098},
{"learn":[0.3136873835],"iteration":376,"passed_time":9.382027317,"remaining_time":15.50398679},
{"learn":[0.3134232455],"iteration":377,"passed_time":9.402580548,"remaining_time":15.47197117},
{"learn":[0.3129065274],"iteration":378,"passed_time":9.422510001,"remaining_time":15.43899396},
{"learn":[0.3127466818],"iteration":379,"passed_time":9.443259685,"remaining_time":15.4074237},
{"learn":[0.3125014436],"iteration":380,"passed_time":9.464169852,"remaining_time":15.37617097},
{"learn":[0.3122738934],"iteration":381,"passed_time":9.483750603,"remaining_time":15.34282166},
{"learn":[0.3119690339],"iteration":382,"passed_time":9.503532176,"remaining_time":15.30986776},
{"learn":[0.3117195782],"iteration":383,"passed_time":9.523178633,"remaining_time":15.27676572},
{"learn":[0.311429095],"iteration":384,"passed_time":9.543982905,"remaining_time":15.24558308},
{"learn":[0.3110288415],"iteration":385,"passed_time":9.568286201,"remaining_time":15.22002002},
{"learn":[0.310727956],"iteration":386,"passed_time":9.590042694,"remaining_time":15.19042938},
{"learn":[0.3103272395],"iteration":387,"passed_time":9.614011702,"remaining_time":15.16436897},
{"learn":[0.3101382645],"iteration":388,"passed_time":9.633083413,"remaining_time":15.13062716},
{"learn":[0.3096691599],"iteration":389,"passed_time":9.656164707,"remaining_time":15.10323198},
{"learn":[0.3095430773],"iteration":390,"passed_time":9.680426046,"remaining_time":15.07769683},
{"learn":[0.309271859],"iteration":391,"passed_time":9.70397458,"remaining_time":15.05106261},
{"learn":[0.3090979424],"iteration":392,"passed_time":9.728946799,"remaining_time":15.02664302},
{"learn":[0.3088913938],"iteration":393,"passed_time":9.753031103,"remaining_time":15.00085494},
{"learn":[0.3085582442],"iteration":394,"passed_time":9.773020315,"remaining_time":14.96880327},
{"learn":[0.3082940361],"iteration":395,"passed_time":9.794914938,"remaining_time":14.93971874},
{"learn":[0.308046685],"iteration":396,"passed_time":9.815387025,"remaining_time":14.90850976},
{"learn":[0.3077615957],"iteration":397,"passed_time":9.837417179,"remaining_time":14.87971141},
{"learn":[0.3075480371],"iteration":398,"passed_time":9.859691578,"remaining_time":14.85131488},
{"learn":[0.3073383592],"iteration":399,"passed_time":9.882908692,"remaining_time":14.82436304},
{"learn":[0.3071193459],"iteration":400,"passed_time":9.907097001,"remaining_time":14.79888056},
{"learn":[0.3067892973],"iteration":401,"passed_time":9.935072438,"remaining_time":14.7790381},
{"learn":[0.306635098],"iteration":402,"passed_time":9.958818086,"remaining_time":14.75288932},
{"learn":[0.3065223353],"iteration":403,"passed_time":9.982292366,"remaining_time":14.7263521},
{"learn":[0.3061672381],"iteration":404,"passed_time":10.00493499,"remaining_time":14.69860819},
{"learn":[0.3055263213],"iteration":405,"passed_time":10.02884714,"remaining_time":14.6727468},
{"learn":[0.305312146],"iteration":406,"passed_time":10.05271577,"remaining_time":14.64683157},
{"learn":[0.3049361997],"iteration":407,"passed_time":10.07591167,"remaining_time":14.61995026},
{"learn":[0.3045763672],"iteration":408,"passed_time":10.09998324,"remaining_time":14.59435232},
{"learn":[0.3042236418],"iteration":409,"passed_time":10.12582279,"remaining_time":14.57130597},
{"learn":[0.3039241906],"iteration":410,"passed_time":10.16478751,"remaining_time":14.56705559},
{"learn":[0.3035969435],"iteration":411,"passed_time":10.19945485,"remaining_time":14.55650353},
{"learn":[0.3032861437],"iteration":412,"passed_time":10.22447405,"remaining_time":14.53212171},
{"learn":[0.3029479023],"iteration":413,"passed_time":10.24587662,"remaining_time":14.50261763},
{"learn":[0.3027505606],"iteration":414,"passed_time":10.27376293,"remaining_time":14.48229232},
{"learn":[0.302540172],"iteration":415,"passed_time":10.30748813,"remaining_time":14.47012756},
{"learn":[0.3023820318],"iteration":416,"passed_time":10.33941858,"remaining_time":14.4553502},
{"learn":[0.3021621245],"iteration":417,"passed_time":10.38484359,"remaining_time":14.45927983},
{"learn":[0.3018715646],"iteration":418,"passed_time":10.42486373,"remaining_time":14.4554793},
{"learn":[0.3017344244],"iteration":419,"passed_time":10.46044576,"remaining_time":14.44537748},
{"learn":[0.3013700585],"iteration":420,"passed_time":10.49421213,"remaining_time":14.43265753},
{"learn":[0.3008953745],"iteration":421,"passed_time":10.53082078,"remaining_time":14.42373083},
{"learn":[0.3007717077],"iteration":422,"passed_time":10.55777518,"remaining_time":14.40150421},
{"learn":[0.3005963315],"iteration":423,"passed_time":10.59965818,"remaining_time":14.39953564},
{"learn":[0.3003970412],"iteration":424,"passed_time":10.62746239,"remaining_time":14.37833147},
{"learn":[0.2999661864],"iteration":425,"passed_time":10.66814957,"remaining_time":14.37445506},
{"learn":[0.299812864],"iteration":426,"passed_time":10.70583544,"remaining_time":14.3663787},
{"learn":[0.299301908],"iteration":427,"passed_time":10.74116153,"remaining_time":14.35501027},
{"learn":[0.2991056126],"iteration":428,"passed_time":10.76497592,"remaining_time":14.32820804},
{"learn":[0.2988945904],"iteration":429,"passed_time":10.78832788,"remaining_time":14.30080673},
{"learn":[0.2987549828],"iteration":430,"passed_time":10.81605532,"remaining_time":14.27920064},
{"learn":[0.2984449206],"iteration":431,"passed_time":10.84222026,"remaining_time":14.25551183},
{"learn":[0.2982497291],"iteration":432,"passed_time":10.86586519,"remaining_time":14.2285117},
{"learn":[0.2980779938],"iteration":433,"passed_time":10.89276318,"remaining_time":14.20576949},
{"learn":[0.2977361877],"iteration":434,"passed_time":10.91479923,"remaining_time":14.17669325},
{"learn":[0.2973286961],"iteration":435,"passed_time":10.93938237,"remaining_time":14.15094417},
{"learn":[0.297127796],"iteration":436,"passed_time":10.96402482,"remaining_time":14.12527683},
{"learn":[0.2969446516],"iteration":437,"passed_time":10.98342716,"remaining_time":14.09289056},
{"learn":[0.2967055333],"iteration":438,"passed_time":11.00735599,"remaining_time":14.06634786},
{"learn":[0.2965508274],"iteration":439,"passed_time":11.0318941,"remaining_time":14.04059249},
{"learn":[0.2962838771],"iteration":440,"passed_time":11.05560557,"remaining_time":14.01379481},
{"learn":[0.2959101688],"iteration":441,"passed_time":11.07640306,"remaining_time":13.98333237},
{"learn":[0.2956736303],"iteration":442,"passed_time":11.10179886,"remaining_time":13.95869518},
{"learn":[0.2952997985],"iteration":443,"passed_time":11.12431951,"remaining_time":13.93045417},
{"learn":[0.2948688822],"iteration":444,"passed_time":11.1505147,"remaining_time":13.9068217},
{"learn":[0.2946865086],"iteration":445,"passed_time":11.17379021,"remaining_time":13.87955106},
{"learn":[0.2944223319],"iteration":446,"passed_time":11.1950366,"remaining_time":13.84978801},
{"learn":[0.2940789217],"iteration":447,"passed_time":11.21670551,"remaining_time":13.82058357},
{"learn":[0.2937884812],"iteration":448,"passed_time":11.23853589,"remaining_time":13.79161086},
{"learn":[0.293592125],"iteration":449,"passed_time":11.2615767,"remaining_time":13.7641493},
{"learn":[0.293519253],"iteration":450,"passed_time":11.28325862,"remaining_time":13.73505318},
{"learn":[0.2931294534],"iteration":451,"passed_time":11.30665821,"remaining_time":13.70807234},
{"learn":[0.292500442],"iteration":452,"passed_time":11.32568594,"remaining_time":13.67582828},
{"learn":[0.2921661284],"iteration":453,"passed_time":11.3490875,"remaining_time":13.64890259},
{"learn":[0.2918414241],"iteration":454,"passed_time":11.37267343,"remaining_time":13.62221323},
{"learn":[0.2916242309],"iteration":455,"passed_time":11.39752925,"remaining_time":13.59705244},
{"learn":[0.291289504],"iteration":456,"passed_time":11.42306658,"remaining_time":13.57270275},
{"learn":[0.290853209],"iteration":457,"passed_time":11.45156386,"remaining_time":13.55185068},
{"learn":[0.2903811294],"iteration":458,"passed_time":11.47384675,"remaining_time":13.52364073},
{"learn":[0.290117317],"iteration":459,"passed_time":11.49497363,"remaining_time":13.49409948},
{"learn":[0.2898446015],"iteration":460,"passed_time":11.51849188,"remaining_time":13.46739072},
{"learn":[0.2896816381],"iteration":461,"passed_time":11.54223017,"remaining_time":13.44095202},
{"learn":[0.2893895706],"iteration":462,"passed_time":11.5656379,"remaining_time":13.41414158},
{"learn":[0.2889695452],"iteration":463,"passed_time":11.59103927,"remaining_time":13.38964881},
{"learn":[0.2887955008],"iteration":464,"passed_time":11.61243235,"remaining_time":13.36054044},
{"learn":[0.2886542622],"iteration":465,"passed_time":11.63516086,"remaining_time":13.33299549},
{"learn":[0.2884295323],"iteration":466,"passed_time":11.65495345,"remaining_time":13.30212031},
{"learn":[0.2881217779],"iteration":467,"passed_time":11.67967031,"remaining_time":13.27689018},
{"learn":[0.2879538043],"iteration":468,"passed_time":11.70182011,"remaining_time":13.24875582},
{"learn":[0.2875864606],"iteration":469,"passed_time":11.7219054,"remaining_time":13.21831885},
{"learn":[0.2873501123],"iteration":470,"passed_time":11.74244352,"remaining_time":13.18843444},
{"learn":[0.2869717978],"iteration":471,"passed_time":11.76188621,"remaining_time":13.15736424},
{"learn":[0.2866149065],"iteration":472,"passed_time":11.78113342,"remaining_time":13.1261254},
{"learn":[0.2865540608],"iteration":473,"passed_time":11.80259805,"remaining_time":13.09739784},
{"learn":[0.2860117992],"iteration":474,"passed_time":11.82193607,"remaining_time":13.06635039},
{"learn":[0.2857445606],"iteration":475,"passed_time":11.84148872,"remaining_time":13.03558842},
{"learn":[0.2854548272],"iteration":476,"passed_time":11.86178817,"remaining_time":13.00569227},
{"learn":[0.2850719284],"iteration":477,"passed_time":11.88377963,"remaining_time":12.97768403},
{"learn":[0.2846486635],"iteration":478,"passed_time":11.90352188,"remaining_time":12.94725449},
{"learn":[0.2843293071],"iteration":479,"passed_time":11.92314728,"remaining_time":12.91674288},
{"learn":[0.2839594301],"iteration":480,"passed_time":11.94541663,"remaining_time":12.88912937},
{"learn":[0.2835144281],"iteration":481,"passed_time":11.96552559,"remaining_time":12.8592163},
{"learn":[0.2833998697],"iteration":482,"passed_time":11.98472115,"remaining_time":12.82836611},
{"learn":[0.2829686609],"iteration":483,"passed_time":12.00580085,"remaining_time":12.79957281},
{"learn":[0.2826587774],"iteration":484,"passed_time":12.02540953,"remaining_time":12.76924929},
{"learn":[0.2825316811],"iteration":485,"passed_time":12.04506058,"remaining_time":12.73901468},
{"learn":[0.2823404661],"iteration":486,"passed_time":12.06647577,"remaining_time":12.71068186},
{"learn":[0.2820654582],"iteration":487,"passed_time":12.08694614,"remaining_time":12.68138611},
{"learn":[0.281646724],"iteration":488,"passed_time":12.10712426,"remaining_time":12.65182106},
{"learn":[0.2815104688],"iteration":489,"passed_time":12.12834453,"remaining_time":12.623379},
{"learn":[0.2811781894],"iteration":490,"passed_time":12.14943973,"remaining_time":12.59483671},
{"learn":[0.2809222156],"iteration":491,"passed_time":12.17089935,"remaining_time":12.56670096},
{"learn":[0.2806018973],"iteration":492,"passed_time":12.19062138,"remaining_time":12.53680536},
{"learn":[0.2803933377],"iteration":493,"passed_time":12.21160493,"remaining_time":12.5082431},
{"learn":[0.2801012759],"iteration":494,"passed_time":12.23245709,"remaining_time":12.47957744},
{"learn":[0.2797452057],"iteration":495,"passed_time":12.2532908,"remaining_time":12.45092452},
{"learn":[0.2794104729],"iteration":496,"passed_time":12.27311032,"remaining_time":12.42127664},
{"learn":[0.2791630538],"iteration":497,"passed_time":12.29476672,"remaining_time":12.39351987},
{"learn":[0.2787956679],"iteration":498,"passed_time":12.31522969,"remaining_time":12.36458933},
{"learn":[0.2784417189],"iteration":499,"passed_time":12.33628165,"remaining_time":12.33628165},
{"learn":[0.2783702247],"iteration":500,"passed_time":12.35603094,"remaining_time":12.30670547},
{"learn":[0.2781854641],"iteration":501,"passed_time":12.37458734,"remaining_time":12.27598505},
{"learn":[0.2779432606],"iteration":502,"passed_time":12.39368147,"remaining_time":12.24584432},
{"learn":[0.2777102637],"iteration":503,"passed_time":12.41524982,"remaining_time":12.21818237},
{"learn":[0.277292205],"iteration":504,"passed_time":12.43416449,"remaining_time":12.18794341},
{"learn":[0.2769000593],"iteration":505,"passed_time":12.45355536,"remaining_time":12.15821413},
{"learn":[0.2767917757],"iteration":506,"passed_time":12.47326668,"remaining_time":12.12883723},
{"learn":[0.2765385116],"iteration":507,"passed_time":12.49188702,"remaining_time":12.09844176},
{"learn":[0.2762992747],"iteration":508,"passed_time":12.51009253,"remaining_time":12.0676924},
{"learn":[0.2760614695],"iteration":509,"passed_time":12.52902691,"remaining_time":12.03769253},
{"learn":[0.2758922736],"iteration":510,"passed_time":12.54762021,"remaining_time":12.00740956},
{"learn":[0.2755602347],"iteration":511,"passed_time":12.56630039,"remaining_time":11.97725505},
{"learn":[0.2750971508],"iteration":512,"passed_time":12.58544513,"remaining_time":11.94758631},
{"learn":[0.274764548],"iteration":513,"passed_time":12.60515244,"remaining_time":11.91849044},
{"learn":[0.2744403377],"iteration":514,"passed_time":12.62475152,"remaining_time":11.8893291},
{"learn":[0.2740858162],"iteration":515,"passed_time":12.64407615,"remaining_time":11.8599474},
{"learn":[0.2739804628],"iteration":516,"passed_time":12.66376297,"remaining_time":11.83094297},
{"learn":[0.2737425304],"iteration":517,"passed_time":12.68295911,"remaining_time":11.80151793},
{"learn":[0.2736030621],"iteration":518,"passed_time":12.70168938,"remaining_time":11.77170056},
{"learn":[0.2733746749],"iteration":519,"passed_time":12.7205944,"remaining_time":11.74208714},
{"learn":[0.2731480944],"iteration":520,"passed_time":12.73903955,"remaining_time":11.71209203},
{"learn":[0.2730694167],"iteration":521,"passed_time":12.75760398,"remaining_time":11.68225039},
{"learn":[0.2728149815],"iteration":522,"passed_time":12.77629712,"remaining_time":11.65256927},
{"learn":[0.2726268443],"iteration":523,"passed_time":12.79466458,"remaining_time":11.62263424},
{"learn":[0.272387408],"iteration":524,"passed_time":12.81339816,"remaining_time":11.59307453},
{"learn":[0.2722373295],"iteration":525,"passed_time":12.83175971,"remaining_time":11.56322072},
{"learn":[0.2719197805],"iteration":526,"passed_time":12.8505822,"remaining_time":11.53382425},
{"learn":[0.2715397754],"iteration":527,"passed_time":12.86959433,"remaining_time":11.50463735},
{"learn":[0.2712818315],"iteration":528,"passed_time":12.88819877,"remaining_time":11.47512594},
{"learn":[0.2709346434],"iteration":529,"passed_time":12.90751027,"remaining_time":11.4462827},
{"learn":[0.2708650087],"iteration":530,"passed_time":12.9266539,"remaining_time":11.41732708},
{"learn":[0.2706769867],"iteration":531,"passed_time":12.94851899,"remaining_time":11.39080242},
{"learn":[0.2704808709],"iteration":532,"passed_time":12.96680745,"remaining_time":11.3611615},
{"learn":[0.2703825613],"iteration":533,"passed_time":12.98587204,"remaining_time":11.33224039},
{"learn":[0.2702523682],"iteration":534,"passed_time":13.00453405,"remaining_time":11.30300623},
{"learn":[0.2699771708],"iteration":535,"passed_time":13.02361728,"remaining_time":11.27417615},
{"learn":[0.2695853558],"iteration":536,"passed_time":13.04299529,"remaining_time":11.24563654},
{"learn":[0.269436255],"iteration":537,"passed_time":13.06152364,"remaining_time":11.21640134},
{"learn":[0.2691973999],"iteration":538,"passed_time":13.08056451,"remaining_time":11.18764423},
{"learn":[0.2689615395],"iteration":539,"passed_time":13.09932731,"remaining_time":11.15868623},
{"learn":[0.2687344277],"iteration":540,"passed_time":13.11782907,"remaining_time":11.12954444},
{"learn":[0.2685659818],"iteration":541,"passed_time":13.13667077,"remaining_time":11.10072917},
{"learn":[0.268292989],"iteration":542,"passed_time":13.15551228,"remaining_time":11.07195049},
{"learn":[0.2680897735],"iteration":543,"passed_time":13.17459723,"remaining_time":11.04341238},
{"learn":[0.2677929871],"iteration":544,"passed_time":13.19368393,"remaining_time":11.01491043},
{"learn":[0.267345021],"iteration":545,"passed_time":13.21338717,"remaining_time":10.98695563},
{"learn":[0.2670347727],"iteration":546,"passed_time":13.23204716,"remaining_time":10.95816703},
{"learn":[0.2669337738],"iteration":547,"passed_time":13.25079452,"remaining_time":10.92948745},
{"learn":[0.2667681739],"iteration":548,"passed_time":13.26970361,"remaining_time":10.90097692},
{"learn":[0.2665445318],"iteration":549,"passed_time":13.28904475,"remaining_time":10.87285479},
{"learn":[0.2662064972],"iteration":550,"passed_time":13.30816898,"remaining_time":10.84458779},
{"learn":[0.2661129074],"iteration":551,"passed_time":13.32623488,"remaining_time":10.81549498},
{"learn":[0.2656043973],"iteration":552,"passed_time":13.34498363,"remaining_time":10.786994},
{"learn":[0.2654436009],"iteration":553,"passed_time":13.36365526,"remaining_time":10.75846615},
{"learn":[0.2651795272],"iteration":554,"passed_time":13.38207885,"remaining_time":10.72977493},
{"learn":[0.2649501936],"iteration":555,"passed_time":13.40136697,"remaining_time":10.70181104},
{"learn":[0.2647272231],"iteration":556,"passed_time":13.42028571,"remaining_time":10.67358451},
{"learn":[0.2646281488],"iteration":557,"passed_time":13.4387483,"remaining_time":10.64503002},
{"learn":[0.2643938043],"iteration":558,"passed_time":13.45760086,"remaining_time":10.61681929},
{"learn":[0.2638337002],"iteration":559,"passed_time":13.47792828,"remaining_time":10.58980079},
{"learn":[0.2636982197],"iteration":560,"passed_time":13.49634207,"remaining_time":10.56130868},
{"learn":[0.2635304792],"iteration":561,"passed_time":13.51455889,"remaining_time":10.53269892},
{"learn":[0.2632483138],"iteration":562,"passed_time":13.53339931,"remaining_time":10.50461012},
{"learn":[0.2629193],"iteration":563,"passed_time":13.55219809,"remaining_time":10.47652193},
{"learn":[0.2627325206],"iteration":564,"passed_time":13.57143817,"remaining_time":10.44880638},
{"learn":[0.2626120297],"iteration":565,"passed_time":13.59006514,"remaining_time":10.42065066},
{"learn":[0.2624109058],"iteration":566,"passed_time":13.60839385,"remaining_time":10.39230077},
{"learn":[0.262193076],"iteration":567,"passed_time":13.62678249,"remaining_time":10.36403175},
{"learn":[0.2620997863],"iteration":568,"passed_time":13.63723818,"remaining_time":10.3297885},
{"learn":[0.2617984698],"iteration":569,"passed_time":13.65609495,"remaining_time":10.30196637},
{"learn":[0.2616044927],"iteration":570,"passed_time":13.67455235,"remaining_time":10.27387559},
{"learn":[0.2612775277],"iteration":571,"passed_time":13.69308114,"remaining_time":10.2458719},
{"learn":[0.2611190619],"iteration":572,"passed_time":13.71123992,"remaining_time":10.21762556},
{"learn":[0.2608520058],"iteration":573,"passed_time":13.73026718,"remaining_time":10.19005892},
{"learn":[0.2605620754],"iteration":574,"passed_time":13.74916356,"remaining_time":10.16242524},
{"learn":[0.2602501181],"iteration":575,"passed_time":13.76818467,"remaining_time":10.13491372},
{"learn":[0.2601154897],"iteration":576,"passed_time":13.78669314,"remaining_time":10.1070558},
{"learn":[0.259922704],"iteration":577,"passed_time":13.80515052,"remaining_time":10.07919294},
{"learn":[0.2598116027],"iteration":578,"passed_time":13.82392067,"remaining_time":10.05158999},
{"learn":[0.2596489125],"iteration":579,"passed_time":13.84251656,"remaining_time":10.0238913},
{"learn":[0.2594221611],"iteration":580,"passed_time":13.86276579,"remaining_time":9.997416291},
{"learn":[0.2592982989],"iteration":581,"passed_time":13.88124558,"remaining_time":9.96969184},
{"learn":[0.2590188576],"iteration":582,"passed_time":13.90006118,"remaining_time":9.942239302},
{"learn":[0.2587644624],"iteration":583,"passed_time":13.918889,"remaining_time":9.914825038},
{"learn":[0.2586096546],"iteration":584,"passed_time":13.9382726,"remaining_time":9.887834407},
{"learn":[0.2583843762],"iteration":585,"passed_time":13.96248485,"remaining_time":9.864281103},
{"learn":[0.2582497139],"iteration":586,"passed_time":13.98462818,"remaining_time":9.839269913},
{"learn":[0.2581017198],"iteration":587,"passed_time":14.00450385,"remaining_time":9.812679566},
{"learn":[0.2580026984],"iteration":588,"passed_time":14.02929422,"remaining_time":9.78954147},
{"learn":[0.2577983322],"iteration":589,"passed_time":14.05235519,"remaining_time":9.765195977},
{"learn":[0.2574621024],"iteration":590,"passed_time":14.08064234,"remaining_time":9.744471603},
{"learn":[0.2570263872],"iteration":591,"passed_time":14.10425768,"remaining_time":9.720501912},
{"learn":[0.2566141939],"iteration":592,"passed_time":14.12493143,"remaining_time":9.694514492},
{"learn":[0.2563795967],"iteration":593,"passed_time":14.14457523,"remaining_time":9.667840983},
{"learn":[0.2560294414],"iteration":594,"passed_time":14.16484508,"remaining_time":9.641617241},
{"learn":[0.2557032243],"iteration":595,"passed_time":14.18539686,"remaining_time":9.615604585},
{"learn":[0.2555779582],"iteration":596,"passed_time":14.21252754,"remaining_time":9.594051253},
{"learn":[0.2554138054],"iteration":597,"passed_time":14.23732809,"remaining_time":9.570912866},
{"learn":[0.2552408266],"iteration":598,"passed_time":14.26069032,"remaining_time":9.546806042},
{"learn":[0.2549548208],"iteration":599,"passed_time":14.28222081,"remaining_time":9.52148054},
{"learn":[0.2548713042],"iteration":600,"passed_time":14.30697051,"remaining_time":9.498304881},
{"learn":[0.254617347],"iteration":601,"passed_time":14.3303772,"remaining_time":9.474236092},
{"learn":[0.2542708822],"iteration":602,"passed_time":14.35123763,"remaining_time":9.448493102},
{"learn":[0.2538025725],"iteration":603,"passed_time":14.37270176,"remaining_time":9.423162083},
{"learn":[0.253689414],"iteration":604,"passed_time":14.39243058,"remaining_time":9.396710872},
{"learn":[0.2533673776],"iteration":605,"passed_time":14.41060571,"remaining_time":9.369271698},
{"learn":[0.2530999686],"iteration":606,"passed_time":14.42996611,"remaining_time":9.342630444},
{"learn":[0.2529239922],"iteration":607,"passed_time":14.44867914,"remaining_time":9.315595764},
{"learn":[0.2526683323],"iteration":608,"passed_time":14.4677459,"remaining_time":9.28881551},
{"learn":[0.2524904829],"iteration":609,"passed_time":14.49249225,"remaining_time":9.265691767},
{"learn":[0.2522606772],"iteration":610,"passed_time":14.51738109,"remaining_time":9.242653426},
{"learn":[0.2520759201],"iteration":611,"passed_time":14.54372008,"remaining_time":9.220528414},
{"learn":[0.2516582568],"iteration":612,"passed_time":14.56638894,"remaining_time":9.196072628},
{"learn":[0.2514428077],"iteration":613,"passed_time":14.59375278,"remaining_time":9.174574222},
{"learn":[0.2513074613],"iteration":614,"passed_time":14.61856508,"remaining_time":9.151459443},
{"learn":[0.2510332194],"iteration":615,"passed_time":14.64172174,"remaining_time":9.12730706},
{"learn":[0.2507676921],"iteration":616,"passed_time":14.66549664,"remaining_time":9.103541674},
{"learn":[0.2506508905],"iteration":617,"passed_time":14.69146896,"remaining_time":9.081134537},
{"learn":[0.2503801112],"iteration":618,"passed_time":14.71480983,"remaining_time":9.057096197},
{"learn":[0.250140269],"iteration":619,"passed_time":14.74198732,"remaining_time":9.035411585},
{"learn":[0.2499414394],"iteration":620,"passed_time":14.76540838,"remaining_time":9.011416707},
{"learn":[0.2497247229],"iteration":621,"passed_time":14.79103082,"remaining_time":8.988761493},
{"learn":[0.2495213652],"iteration":622,"passed_time":14.8134629,"remaining_time":8.964166154},
{"learn":[0.24928264],"iteration":623,"passed_time":14.83798516,"remaining_time":8.940837213},
{"learn":[0.2491689774],"iteration":624,"passed_time":14.86475837,"remaining_time":8.918855024},
{"learn":[0.2489635279],"iteration":625,"passed_time":14.89510963,"remaining_time":8.898995212},
{"learn":[0.2484694046],"iteration":626,"passed_time":14.94682664,"remaining_time":8.891812341},
{"learn":[0.2481865731],"iteration":627,"passed_time":14.97150524,"remaining_time":8.868471255},
{"learn":[0.2477108864],"iteration":628,"passed_time":14.99416931,"remaining_time":8.8439377},
{"learn":[0.2475801789],"iteration":629,"passed_time":15.01821825,"remaining_time":8.820223414},
{"learn":[0.2474040341],"iteration":630,"passed_time":15.04516076,"remaining_time":8.79820019},
{"learn":[0.247015176],"iteration":631,"passed_time":15.07147392,"remaining_time":8.775794939},
{"learn":[0.2467410653],"iteration":632,"passed_time":15.09378267,"remaining_time":8.751055673},
{"learn":[0.246572452],"iteration":633,"passed_time":15.12351887,"remaining_time":8.730611842},
{"learn":[0.2464303214],"iteration":634,"passed_time":15.14941578,"remaining_time":8.707931905},
{"learn":[0.2461723755],"iteration":635,"passed_time":15.17455728,"remaining_time":8.684809513},
{"learn":[0.24583156],"iteration":636,"passed_time":15.20006601,"remaining_time":8.661890052},
{"learn":[0.2456853643],"iteration":637,"passed_time":15.22423581,"remaining_time":8.638202764},
{"learn":[0.2452591251],"iteration":638,"passed_time":15.2458145,"remaining_time":8.613050132},
{"learn":[0.2450676393],"iteration":639,"passed_time":15.27132673,"remaining_time":8.590121284},
{"learn":[0.2448873106],"iteration":640,"passed_time":15.29701324,"remaining_time":8.567281984},
{"learn":[0.2446847755],"iteration":641,"passed_time":15.32303839,"remaining_time":8.544622653},
{"learn":[0.2445730435],"iteration":642,"passed_time":15.34700444,"remaining_time":8.520809619},
{"learn":[0.2444076159],"iteration":643,"passed_time":15.37042895,"remaining_time":8.496696747},
{"learn":[0.2440818898],"iteration":644,"passed_time":15.39260576,"remaining_time":8.471899294},
{"learn":[0.2438659092],"iteration":645,"passed_time":15.41539354,"remaining_time":8.44744476},
{"learn":[0.243415106],"iteration":646,"passed_time":15.43826288,"remaining_time":8.423039874},
{"learn":[0.2432868158],"iteration":647,"passed_time":15.46135346,"remaining_time":8.398759906},
{"learn":[0.2429739853],"iteration":648,"passed_time":15.486409,"remaining_time":8.375546318},
{"learn":[0.2425477151],"iteration":649,"passed_time":15.51238934,"remaining_time":8.352825029},
{"learn":[0.2424177286],"iteration":650,"passed_time":15.53937485,"remaining_time":8.330632602},
{"learn":[0.2421949686],"iteration":651,"passed_time":15.56824109,"remaining_time":8.309429291},
{"learn":[0.2418502954],"iteration":652,"passed_time":15.59354994,"remaining_time":8.286312144},
{"learn":[0.2416440454],"iteration":653,"passed_time":15.62102678,"remaining_time":8.264335271},
{"learn":[0.2414691889],"iteration":654,"passed_time":15.65317732,"remaining_time":8.244803323},
{"learn":[0.2411153363],"iteration":655,"passed_time":15.67609853,"remaining_time":8.220393132},
{"learn":[0.2407380782],"iteration":656,"passed_time":15.70650344,"remaining_time":8.199894491},
{"learn":[0.2403939794],"iteration":657,"passed_time":15.74068155,"remaining_time":8.181326887},
{"learn":[0.2403400059],"iteration":658,"passed_time":15.77350334,"remaining_time":8.162010074},
{"learn":[0.240077827],"iteration":659,"passed_time":15.79750087,"remaining_time":8.138106508},
{"learn":[0.2399400221],"iteration":660,"passed_time":15.8233646,"remaining_time":8.115159756},
{"learn":[0.239765567],"iteration":661,"passed_time":15.8475808,"remaining_time":8.091363009},
{"learn":[0.2395044631],"iteration":662,"passed_time":15.87543427,"remaining_time":8.069413798},
{"learn":[0.2393913959],"iteration":663,"passed_time":15.90688922,"remaining_time":8.049269244},
{"learn":[0.2391594343],"iteration":664,"passed_time":15.94198686,"remaining_time":8.03092571},
{"learn":[0.2388355346],"iteration":665,"passed_time":16.00466278,"remaining_time":8.026362413},
{"learn":[0.2385794353],"iteration":666,"passed_time":16.03501249,"remaining_time":8.005485997},
{"learn":[0.2383865574],"iteration":667,"passed_time":16.06841388,"remaining_time":7.986097914},
{"learn":[0.2382144345],"iteration":668,"passed_time":16.0963429,"remaining_time":7.963960387},
{"learn":[0.2379676218],"iteration":669,"passed_time":16.13479893,"remaining_time":7.946990518},
{"learn":[0.2376207946],"iteration":670,"passed_time":16.16755611,"remaining_time":7.927162387},
{"learn":[0.2374220669],"iteration":671,"passed_time":16.19748841,"remaining_time":7.90591696},
{"learn":[0.2371617889],"iteration":672,"passed_time":16.22534575,"remaining_time":7.883637534},
{"learn":[0.2368947849],"iteration":673,"passed_time":16.25634568,"remaining_time":7.862861563},
{"learn":[0.2366346156],"iteration":674,"passed_time":16.28748188,"remaining_time":7.842120905},
{"learn":[0.2362948194],"iteration":675,"passed_time":16.32342669,"remaining_time":7.823654212},
{"learn":[0.2361109924],"iteration":676,"passed_time":16.35712242,"remaining_time":7.804062838},
{"learn":[0.2359593666],"iteration":677,"passed_time":16.38999122,"remaining_time":7.784037127},
{"learn":[0.2358242131],"iteration":678,"passed_time":16.41899203,"remaining_time":7.762144978},
{"learn":[0.2355284484],"iteration":679,"passed_time":16.44435547,"remaining_time":7.738520219},
{"learn":[0.2353602418],"iteration":680,"passed_time":16.46980241,"remaining_time":7.714929471},
{"learn":[0.2350689227],"iteration":681,"passed_time":16.50223392,"remaining_time":7.694590009},
{"learn":[0.2348535918],"iteration":682,"passed_time":16.52751565,"remaining_time":7.67089672},
{"learn":[0.2346412708],"iteration":683,"passed_time":16.55739551,"remaining_time":7.64932307},
{"learn":[0.234361974],"iteration":684,"passed_time":16.59079511,"remaining_time":7.629343736},
{"learn":[0.2341023155],"iteration":685,"passed_time":16.62180506,"remaining_time":7.608231469},
{"learn":[0.2339307586],"iteration":686,"passed_time":16.65112542,"remaining_time":7.586320606},
{"learn":[0.2335944809],"iteration":687,"passed_time":16.67513862,"remaining_time":7.561981469},
{"learn":[0.2332165952],"iteration":688,"passed_time":16.70431882,"remaining_time":7.539975549},
{"learn":[0.2329309056],"iteration":689,"passed_time":16.73544933,"remaining_time":7.518825061},
{"learn":[0.2326977863],"iteration":690,"passed_time":16.77336767,"remaining_time":7.500681057},
{"learn":[0.2325376664],"iteration":691,"passed_time":16.80825823,"remaining_time":7.481132274},
{"learn":[0.2323634323],"iteration":692,"passed_time":16.84052125,"remaining_time":7.460375216},
{"learn":[0.2319501114],"iteration":693,"passed_time":16.87167031,"remaining_time":7.439093826},
{"learn":[0.231717338],"iteration":694,"passed_time":16.90334207,"remaining_time":7.418013427},
{"learn":[0.2315278937],"iteration":695,"passed_time":16.93525198,"remaining_time":7.397006611},
{"learn":[0.2313608515],"iteration":696,"passed_time":16.96405132,"remaining_time":7.374616284},
{"learn":[0.2310728886],"iteration":697,"passed_time":16.99665215,"remaining_time":7.353852365},
{"learn":[0.230902637],"iteration":698,"passed_time":17.02591002,"remaining_time":7.331615045},
{"learn":[0.2306849406],"iteration":699,"passed_time":17.05040076,"remaining_time":7.307314612},
{"learn":[0.2305582225],"iteration":700,"passed_time":17.08137963,"remaining_time":7.285781039},
{"learn":[0.2304588813],"iteration":701,"passed_time":17.10867923,"remaining_time":7.262658705},
{"learn":[0.2302880968],"iteration":702,"passed_time":17.13780906,"remaining_time":7.240297713},
{"learn":[0.2300775468],"iteration":703,"passed_time":17.16868857,"remaining_time":7.218653149},
{"learn":[0.2298000584],"iteration":704,"passed_time":17.19905906,"remaining_time":7.196769394},
{"learn":[0.2295775743],"iteration":705,"passed_time":17.22992488,"remaining_time":7.175067869},
{"learn":[0.2294229908],"iteration":706,"passed_time":17.25485775,"remaining_time":7.150881644},
{"learn":[0.2292425282],"iteration":707,"passed_time":17.28353986,"remaining_time":7.128239602},
{"learn":[0.2290851325],"iteration":708,"passed_time":17.31392029,"remaining_time":7.10627758},
{"learn":[0.2288860213],"iteration":709,"passed_time":17.34853036,"remaining_time":7.086019442},
{"learn":[0.228666445],"iteration":710,"passed_time":17.38010276,"remaining_time":7.064486213},
{"learn":[0.2285689697],"iteration":711,"passed_time":17.40375213,"remaining_time":7.039719963},
{"learn":[0.2283295224],"iteration":712,"passed_time":17.43156141,"remaining_time":7.016631309},
{"learn":[0.2282476184],"iteration":713,"passed_time":17.45330426,"remaining_time":6.991099466},
{"learn":[0.2280181526],"iteration":714,"passed_time":17.48383518,"remaining_time":6.969081157},
{"learn":[0.227835958],"iteration":715,"passed_time":17.50897184,"remaining_time":6.944899447},
{"learn":[0.2277395121],"iteration":716,"passed_time":17.54040799,"remaining_time":6.92320148},
{"learn":[0.2274477629],"iteration":717,"passed_time":17.56881539,"remaining_time":6.900286825},
{"learn":[0.2272684878],"iteration":718,"passed_time":17.59616395,"remaining_time":6.876943074},
{"learn":[0.2271509849],"iteration":719,"passed_time":17.62148589,"remaining_time":6.852800068},
{"learn":[0.2270043987],"iteration":720,"passed_time":17.65407782,"remaining_time":6.831467005},
{"learn":[0.2268385755],"iteration":721,"passed_time":17.68192774,"remaining_time":6.808276888},
{"learn":[0.2265814127],"iteration":722,"passed_time":17.70857699,"remaining_time":6.784613867},
{"learn":[0.2263910245],"iteration":723,"passed_time":17.73518768,"remaining_time":6.760927901},
{"learn":[0.225978195],"iteration":724,"passed_time":17.76245884,"remaining_time":6.737484387},
{"learn":[0.2258064634],"iteration":725,"passed_time":17.78866399,"remaining_time":6.713628007},
{"learn":[0.2256029258],"iteration":726,"passed_time":17.81687289,"remaining_time":6.690517607},
{"learn":[0.2252782326],"iteration":727,"passed_time":17.8456213,"remaining_time":6.667594771},
{"learn":[0.2251377218],"iteration":728,"passed_time":17.87557095,"remaining_time":6.645102505},
{"learn":[0.2249281736],"iteration":729,"passed_time":17.90404016,"remaining_time":6.622042251},
{"learn":[0.2247813568],"iteration":730,"passed_time":17.93226321,"remaining_time":6.598876614},
{"learn":[0.2246411439],"iteration":731,"passed_time":17.96259049,"remaining_time":6.576467558},
{"learn":[0.224500111],"iteration":732,"passed_time":17.99409623,"remaining_time":6.554466158},
{"learn":[0.2241706009],"iteration":733,"passed_time":18.02093593,"remaining_time":6.530747899},
{"learn":[0.2240894246],"iteration":734,"passed_time":18.04873096,"remaining_time":6.507365584},
{"learn":[0.2236998895],"iteration":735,"passed_time":18.07853693,"remaining_time":6.484692593},
{"learn":[0.2235948878],"iteration":736,"passed_time":18.10900423,"remaining_time":6.462236244},
{"learn":[0.2233221626],"iteration":737,"passed_time":18.13595219,"remaining_time":6.438508771},
{"learn":[0.222992018],"iteration":738,"passed_time":18.16504285,"remaining_time":6.415529343},
{"learn":[0.2227537867],"iteration":739,"passed_time":18.19297748,"remaining_time":6.392127223},
{"learn":[0.2225287662],"iteration":740,"passed_time":18.21473267,"remaining_time":6.366552983},
{"learn":[0.2223318048],"iteration":741,"passed_time":18.24137371,"remaining_time":6.342687893},
{"learn":[0.222072607],"iteration":742,"passed_time":18.26726078,"remaining_time":6.318554536},
{"learn":[0.2219365158],"iteration":743,"passed_time":18.29578757,"remaining_time":6.295324754},
{"learn":[0.221629059],"iteration":744,"passed_time":18.32068649,"remaining_time":6.270839001},
{"learn":[0.2214947129],"iteration":745,"passed_time":18.34381595,"remaining_time":6.245749665},
{"learn":[0.2213782704],"iteration":746,"passed_time":18.37517126,"remaining_time":6.223451577},
{"learn":[0.2212590819],"iteration":747,"passed_time":18.40186844,"remaining_time":6.199559954},
{"learn":[0.2210403664],"iteration":748,"passed_time":18.43176055,"remaining_time":6.176731507},
{"learn":[0.2206219838],"iteration":749,"passed_time":18.46259472,"remaining_time":6.154198242},
{"learn":[0.2204151249],"iteration":750,"passed_time":18.49477776,"remaining_time":6.132090095},
{"learn":[0.2199749679],"iteration":751,"passed_time":18.51928664,"remaining_time":6.107424317},
{"learn":[0.2196406432],"iteration":752,"passed_time":18.54624293,"remaining_time":6.083561758},
{"learn":[0.2194064523],"iteration":753,"passed_time":18.57501536,"remaining_time":6.060283526},
{"learn":[0.2190919863],"iteration":754,"passed_time":18.59808868,"remaining_time":6.03514136},
{"learn":[0.2188856409],"iteration":755,"passed_time":18.62570623,"remaining_time":6.011471322},
{"learn":[0.2185516528],"iteration":756,"passed_time":18.65213042,"remaining_time":5.987407784},
{"learn":[0.2184065483],"iteration":757,"passed_time":18.67513764,"remaining_time":5.96224711},
{"learn":[0.2179301946],"iteration":758,"passed_time":18.70105442,"remaining_time":5.938015963},
{"learn":[0.2178467792],"iteration":759,"passed_time":18.72620377,"remaining_time":5.913538033},
{"learn":[0.2175883542],"iteration":760,"passed_time":18.7785936,"remaining_time":5.897613497},
{"learn":[0.2174860128],"iteration":761,"passed_time":18.80512274,"remaining_time":5.873516027},
{"learn":[0.2173233116],"iteration":762,"passed_time":18.83647802,"remaining_time":5.850911258},
{"learn":[0.2171917329],"iteration":763,"passed_time":18.8621383,"remaining_time":5.826524396},
{"learn":[0.2169023229],"iteration":764,"passed_time":18.89596046,"remaining_time":5.804641449},
{"learn":[0.2168051699],"iteration":765,"passed_time":18.92594646,"remaining_time":5.781555445},
{"learn":[0.2167261383],"iteration":766,"passed_time":18.95779683,"remaining_time":5.759017812},
{"learn":[0.2164582984],"iteration":767,"passed_time":18.98579283,"remaining_time":5.735291584},
{"learn":[0.216365258],"iteration":768,"passed_time":19.01225311,"remaining_time":5.711092938},
{"learn":[0.2159659348],"iteration":769,"passed_time":19.03989107,"remaining_time":5.687240191},
{"learn":[0.2157411423],"iteration":770,"passed_time":19.06705151,"remaining_time":5.663235793},
{"learn":[0.2153224754],"iteration":771,"passed_time":19.09557347,"remaining_time":5.639625327},
{"learn":[0.2150504665],"iteration":772,"passed_time":19.12505356,"remaining_time":5.616283515},
{"learn":[0.2149231266],"iteration":773,"passed_time":19.14988726,"remaining_time":5.591569148},
{"learn":[0.2145995471],"iteration":774,"passed_time":19.17804301,"remaining_time":5.567818939},
{"learn":[0.214340246],"iteration":775,"passed_time":19.2050497,"remaining_time":5.543725686},
{"learn":[0.2141149144],"iteration":776,"passed_time":19.23024529,"remaining_time":5.519105149},
{"learn":[0.214043321],"iteration":777,"passed_time":19.25813135,"remaining_time":5.495250847},
{"learn":[0.2137320921],"iteration":778,"passed_time":19.28188273,"remaining_time":5.470213201},
{"learn":[0.2135373375],"iteration":779,"passed_time":19.30912927,"remaining_time":5.446164665},
{"learn":[0.2134345845],"iteration":780,"passed_time":19.33780737,"remaining_time":5.422509364},
{"learn":[0.2133382004],"iteration":781,"passed_time":19.36160754,"remaining_time":5.397481387},
{"learn":[0.2131329787],"iteration":782,"passed_time":19.38927761,"remaining_time":5.373529044},
{"learn":[0.2129762924],"iteration":783,"passed_time":19.41340953,"remaining_time":5.348592421},
{"learn":[0.2127936981],"iteration":784,"passed_time":19.44141828,"remaining_time":5.324719655},
{"learn":[0.2126947256],"iteration":785,"passed_time":19.46813782,"remaining_time":5.300485361},
{"learn":[0.2125478165],"iteration":786,"passed_time":19.49257256,"remaining_time":5.275626372},
{"learn":[0.2122751502],"iteration":787,"passed_time":19.51937043,"remaining_time":5.251404227},
{"learn":[0.2120293443],"iteration":788,"passed_time":19.54370203,"remaining_time":5.226516006},
{"learn":[0.211877263],"iteration":789,"passed_time":19.57326785,"remaining_time":5.203020567},
{"learn":[0.2116436384],"iteration":790,"passed_time":19.59664153,"remaining_time":5.177873679},
{"learn":[0.2114806418],"iteration":791,"passed_time":19.62381465,"remaining_time":5.153729099},
{"learn":[0.2113107153],"iteration":792,"passed_time":19.65139647,"remaining_time":5.129683568},
{"learn":[0.2112156854],"iteration":793,"passed_time":19.67595356,"remaining_time":5.104844373},
{"learn":[0.2109948455],"iteration":794,"passed_time":19.70397339,"remaining_time":5.080898798},
{"learn":[0.2107375279],"iteration":795,"passed_time":19.7291356,"remaining_time":5.056210631},
{"learn":[0.210525729],"iteration":796,"passed_time":19.75746319,"remaining_time":5.032327512},
{"learn":[0.2103914123],"iteration":797,"passed_time":19.78394931,"remaining_time":5.007967118},
{"learn":[0.2102652651],"iteration":798,"passed_time":19.80784995,"remaining_time":4.982950989},
{"learn":[0.2100098515],"iteration":799,"passed_time":19.83778186,"remaining_time":4.959445464},
{"learn":[0.209810138],"iteration":800,"passed_time":19.86074832,"remaining_time":4.934193403},
{"learn":[0.2095152793],"iteration":801,"passed_time":19.88813023,"remaining_time":4.910037139},
{"learn":[0.2093613687],"iteration":802,"passed_time":19.91274969,"remaining_time":4.88519513},
{"learn":[0.2090579132],"iteration":803,"passed_time":19.93866547,"remaining_time":4.860669691},
{"learn":[0.2087640767],"iteration":804,"passed_time":19.96867443,"remaining_time":4.837132315},
{"learn":[0.2086186723],"iteration":805,"passed_time":19.99346035,"remaining_time":4.812321721},
{"learn":[0.2084274476],"iteration":806,"passed_time":20.0210984,"remaining_time":4.788193297},
{"learn":[0.2083738739],"iteration":807,"passed_time":20.0484528,"remaining_time":4.763988784},
{"learn":[0.2082557713],"iteration":808,"passed_time":20.0742808,"remaining_time":4.73941611},
{"learn":[0.2080232572],"iteration":809,"passed_time":20.10125193,"remaining_time":4.715108478},
{"learn":[0.2078750682],"iteration":810,"passed_time":20.1252201,"remaining_time":4.69009445},
{"learn":[0.2077626422],"iteration":811,"passed_time":20.15403086,"remaining_time":4.66620419},
{"learn":[0.2074480638],"iteration":812,"passed_time":20.18058961,"remaining_time":4.641783834},
{"learn":[0.2071026621],"iteration":813,"passed_time":20.20826431,"remaining_time":4.617613221},
{"learn":[0.20700202],"iteration":814,"passed_time":20.23658209,"remaining_time":4.593579983},
{"learn":[0.2068041651],"iteration":815,"passed_time":20.25937529,"remaining_time":4.568290507},
{"learn":[0.2064440246],"iteration":816,"passed_time":20.28729036,"remaining_time":4.54415439},
{"learn":[0.2061688646],"iteration":817,"passed_time":20.31517482,"remaining_time":4.520002221},
{"learn":[0.2060861292],"iteration":818,"passed_time":20.33765187,"remaining_time":4.494645896},
{"learn":[0.2060323733],"iteration":819,"passed_time":20.36737225,"remaining_time":4.470886591},
{"learn":[0.2058897506],"iteration":820,"passed_time":20.39147329,"remaining_time":4.445887599},
{"learn":[0.205799526],"iteration":821,"passed_time":20.41967919,"remaining_time":4.421779679},
{"learn":[0.2057177004],"iteration":822,"passed_time":20.44936246,"remaining_time":4.397979533},
{"learn":[0.2056534028],"iteration":823,"passed_time":20.47394624,"remaining_time":4.373075896},
{"learn":[0.2054124962],"iteration":824,"passed_time":20.50335482,"remaining_time":4.349196477},
{"learn":[0.2050494737],"iteration":825,"passed_time":20.53151744,"remaining_time":4.325041204},
{"learn":[0.2047067676],"iteration":826,"passed_time":20.56438501,"remaining_time":4.301860468},
{"learn":[0.2045567411],"iteration":827,"passed_time":20.5902906,"remaining_time":4.277210125},
{"learn":[0.2041793679],"iteration":828,"passed_time":20.61933456,"remaining_time":4.253204112},
{"learn":[0.2039929754],"iteration":829,"passed_time":20.65213528,"remaining_time":4.229955418},
{"learn":[0.2036073552],"iteration":830,"passed_time":20.68072783,"remaining_time":4.205827922},
{"learn":[0.203278395],"iteration":831,"passed_time":20.70644858,"remaining_time":4.18110981},
{"learn":[0.2031250166],"iteration":832,"passed_time":20.73551094,"remaining_time":4.157059216},
{"learn":[0.2029952975],"iteration":833,"passed_time":20.76570874,"remaining_time":4.133222602},
{"learn":[0.2028266175],"iteration":834,"passed_time":20.78882561,"remaining_time":4.107971528},
{"learn":[0.202704897],"iteration":835,"passed_time":20.81548932,"remaining_time":4.083421349},
{"learn":[0.2023999869],"iteration":836,"passed_time":20.84252009,"remaining_time":4.058937604},
{"learn":[0.2022402625],"iteration":837,"passed_time":20.86594758,"remaining_time":4.033751203},
{"learn":[0.2019067766],"iteration":838,"passed_time":20.88786242,"remaining_time":4.008278725},
{"learn":[0.2017351667],"iteration":839,"passed_time":20.90910944,"remaining_time":3.982687512},
{"learn":[0.2015662008],"iteration":840,"passed_time":20.92924454,"remaining_time":3.956896412},
{"learn":[0.2013266654],"iteration":841,"passed_time":20.94975367,"remaining_time":3.931188931},
{"learn":[0.2011151039],"iteration":842,"passed_time":20.9696722,"remaining_time":3.90538379},
{"learn":[0.2008736061],"iteration":843,"passed_time":20.99049152,"remaining_time":3.879759097},
{"learn":[0.2006577165],"iteration":844,"passed_time":21.01179491,"remaining_time":3.854234568},
{"learn":[0.2004747286],"iteration":845,"passed_time":21.03140269,"remaining_time":3.828411365},
{"learn":[0.2003905087],"iteration":846,"passed_time":21.05184468,"remaining_time":3.802753525},
{"learn":[0.200349308],"iteration":847,"passed_time":21.07173752,"remaining_time":3.777009556},
{"learn":[0.1999420869],"iteration":848,"passed_time":21.09318768,"remaining_time":3.751556348},
{"learn":[0.1997629515],"iteration":849,"passed_time":21.11481547,"remaining_time":3.726143906},
{"learn":[0.1996966307],"iteration":850,"passed_time":21.1365456,"remaining_time":3.700758278},
{"learn":[0.1996004838],"iteration":851,"passed_time":21.16388954,"remaining_time":3.676356399},
{"learn":[0.1993432446],"iteration":852,"passed_time":21.18808946,"remaining_time":3.651405804},
{"learn":[0.1991433565],"iteration":853,"passed_time":21.21680679,"remaining_time":3.627229264},
{"learn":[0.1989690843],"iteration":854,"passed_time":21.24432187,"remaining_time":3.602838213},
{"learn":[0.198647433],"iteration":855,"passed_time":21.2713638,"remaining_time":3.578360265},
{"learn":[0.1984326083],"iteration":856,"passed_time":21.30316056,"remaining_time":3.554669732},
{"learn":[0.1982323408],"iteration":857,"passed_time":21.33015531,"remaining_time":3.530165564},
{"learn":[0.1980253072],"iteration":858,"passed_time":21.35601136,"remaining_time":3.505468687},
{"learn":[0.1979229989],"iteration":859,"passed_time":21.38301251,"remaining_time":3.480955525},
{"learn":[0.1978485938],"iteration":860,"passed_time":21.4028979,"remaining_time":3.455287814},
{"learn":[0.1976782152],"iteration":861,"passed_time":21.42434322,"remaining_time":3.429883253},
{"learn":[0.1975655671],"iteration":862,"passed_time":21.44534052,"remaining_time":3.404416746},
{"learn":[0.1974453264],"iteration":863,"passed_time":21.46474528,"remaining_time":3.378709906},
{"learn":[0.1973559336],"iteration":864,"passed_time":21.48541512,"remaining_time":3.353215077},
{"learn":[0.1971431544],"iteration":865,"passed_time":21.50718648,"remaining_time":3.327901834},
{"learn":[0.1968685813],"iteration":866,"passed_time":21.52660115,"remaining_time":3.30223524},
{"learn":[0.196663182],"iteration":867,"passed_time":21.54792318,"remaining_time":3.27687311},
{"learn":[0.1965416768],"iteration":868,"passed_time":21.56808249,"remaining_time":3.251345002},
{"learn":[0.1963482051],"iteration":869,"passed_time":21.58879058,"remaining_time":3.225911237},
{"learn":[0.1961072376],"iteration":870,"passed_time":21.60991047,"remaining_time":3.200549311},
{"learn":[0.1958294001],"iteration":871,"passed_time":21.62954555,"remaining_time":3.174979163},
{"learn":[0.1956834886],"iteration":872,"passed_time":21.6498591,"remaining_time":3.149521312},
{"learn":[0.1954966533],"iteration":873,"passed_time":21.67021674,"remaining_time":3.12408159},
{"learn":[0.1953264981],"iteration":874,"passed_time":21.69164888,"remaining_time":3.098806983},
{"learn":[0.195230191],"iteration":875,"passed_time":21.71289102,"remaining_time":3.073514253},
{"learn":[0.195056895],"iteration":876,"passed_time":21.73770697,"remaining_time":3.048731992},
{"learn":[0.194748002],"iteration":877,"passed_time":21.76173275,"remaining_time":3.023839858},
{"learn":[0.1946181193],"iteration":878,"passed_time":21.7836338,"remaining_time":2.998657213},
{"learn":[0.1944559632],"iteration":879,"passed_time":21.80775616,"remaining_time":2.973784931},
{"learn":[0.1943867096],"iteration":880,"passed_time":21.83092446,"remaining_time":2.948785484},
{"learn":[0.1943322246],"iteration":881,"passed_time":21.85273525,"remaining_time":2.923608571},
{"learn":[0.1942584304],"iteration":882,"passed_time":21.87544399,"remaining_time":2.898558263},
{"learn":[0.1941013154],"iteration":883,"passed_time":21.89573901,"remaining_time":2.873196521},
{"learn":[0.1939538997],"iteration":884,"passed_time":21.91619009,"remaining_time":2.847866509},
{"learn":[0.1938421246],"iteration":885,"passed_time":21.93749579,"remaining_time":2.822657472},
{"learn":[0.1934896804],"iteration":886,"passed_time":21.95763465,"remaining_time":2.797308586},
{"learn":[0.1933442072],"iteration":887,"passed_time":21.97793104,"remaining_time":2.771991302},
{"learn":[0.1928886077],"iteration":888,"passed_time":21.99835624,"remaining_time":2.746701398},
{"learn":[0.1927643028],"iteration":889,"passed_time":22.02045356,"remaining_time":2.721629092},
{"learn":[0.1925223235],"iteration":890,"passed_time":22.04055022,"remaining_time":2.696318714},
{"learn":[0.1924189579],"iteration":891,"passed_time":22.06019855,"remaining_time":2.670965743},
{"learn":[0.1922927131],"iteration":892,"passed_time":22.08107201,"remaining_time":2.645772346},
{"learn":[0.1921132107],"iteration":893,"passed_time":22.10159155,"remaining_time":2.62054665},
{"learn":[0.1920096866],"iteration":894,"passed_time":22.12184166,"remaining_time":2.595299859},
{"learn":[0.1917256459],"iteration":895,"passed_time":22.14261755,"remaining_time":2.570125252},
{"learn":[0.1916472713],"iteration":896,"passed_time":22.1642033,"remaining_time":2.545053445},
{"learn":[0.1915014732],"iteration":897,"passed_time":22.18442273,"remaining_time":2.519834208},
{"learn":[0.1914085039],"iteration":898,"passed_time":22.20553263,"remaining_time":2.494726135},
{"learn":[0.1913679517],"iteration":899,"passed_time":22.22543109,"remaining_time":2.469492344},
{"learn":[0.1912550311],"iteration":900,"passed_time":22.24577051,"remaining_time":2.444318846},
{"learn":[0.1911140218],"iteration":901,"passed_time":22.27006991,"remaining_time":2.41958631},
{"learn":[0.1909266229],"iteration":902,"passed_time":22.29460842,"remaining_time":2.394880417},
{"learn":[0.1906802372],"iteration":903,"passed_time":22.32288308,"remaining_time":2.370571655},
{"learn":[0.1905709198],"iteration":904,"passed_time":22.35003885,"remaining_time":2.346136675},
{"learn":[0.1904713107],"iteration":905,"passed_time":22.3756295,"remaining_time":2.321533303},
{"learn":[0.1904149972],"iteration":906,"passed_time":22.40307194,"remaining_time":2.29711763},
{"learn":[0.1903200546],"iteration":907,"passed_time":22.42883636,"remaining_time":2.27252527},
{"learn":[0.1902014291],"iteration":908,"passed_time":22.45491753,"remaining_time":2.247962041},
{"learn":[0.1900246906],"iteration":909,"passed_time":22.48070947,"remaining_time":2.223366871},
{"learn":[0.1898002277],"iteration":910,"passed_time":22.50761057,"remaining_time":2.198877432},
{"learn":[0.189671721],"iteration":911,"passed_time":22.53125921,"remaining_time":2.174068871},
{"learn":[0.1895461076],"iteration":912,"passed_time":22.5539764,"remaining_time":2.149174093},
{"learn":[0.1894214628],"iteration":913,"passed_time":22.57398362,"remaining_time":2.124029093},
{"learn":[0.1893074333],"iteration":914,"passed_time":22.59423079,"remaining_time":2.098917614},
{"learn":[0.189161065],"iteration":915,"passed_time":22.61448013,"remaining_time":2.073816956},
{"learn":[0.1889802414],"iteration":916,"passed_time":22.63657656,"remaining_time":2.048894061},
{"learn":[0.1888945404],"iteration":917,"passed_time":22.65752165,"remaining_time":2.023874483},
{"learn":[0.1886409571],"iteration":918,"passed_time":22.67736095,"remaining_time":1.998766308},
{"learn":[0.1882915783],"iteration":919,"passed_time":22.69822968,"remaining_time":1.973759102},
{"learn":[0.1881424713],"iteration":920,"passed_time":22.71956589,"remaining_time":1.948800983},
{"learn":[0.1880033543],"iteration":921,"passed_time":22.73929816,"remaining_time":1.923715028},
{"learn":[0.1877871622],"iteration":922,"passed_time":22.76020455,"remaining_time":1.898738624},
{"learn":[0.1875497677],"iteration":923,"passed_time":22.78051715,"remaining_time":1.87372219},
{"learn":[0.1873851565],"iteration":924,"passed_time":22.80193446,"remaining_time":1.848805497},
{"learn":[0.1870676271],"iteration":925,"passed_time":22.82392531,"remaining_time":1.823942195},
{"learn":[0.1869617026],"iteration":926,"passed_time":22.84387106,"remaining_time":1.798924043},
{"learn":[0.186779099],"iteration":927,"passed_time":22.86402018,"remaining_time":1.7739326},
{"learn":[0.186687144],"iteration":928,"passed_time":22.88598931,"remaining_time":1.749090679},
{"learn":[0.1866252649],"iteration":929,"passed_time":22.90667602,"remaining_time":1.72415841},
{"learn":[0.1866002252],"iteration":930,"passed_time":22.92682913,"remaining_time":1.699195715},
{"learn":[0.186536123],"iteration":931,"passed_time":22.94722568,"remaining_time":1.674261101},
{"learn":[0.1865151876],"iteration":932,"passed_time":22.96933208,"remaining_time":1.649459003},
{"learn":[0.1862708703],"iteration":933,"passed_time":22.98949539,"remaining_time":1.62452537},
{"learn":[0.1862280935],"iteration":934,"passed_time":23.0100704,"remaining_time":1.599630563},
{"learn":[0.1859639844],"iteration":935,"passed_time":23.0316934,"remaining_time":1.574816643},
{"learn":[0.1858245962],"iteration":936,"passed_time":23.05253735,"remaining_time":1.549957154},
{"learn":[0.1855928668],"iteration":937,"passed_time":23.07240038,"remaining_time":1.52504139},
{"learn":[0.1854124538],"iteration":938,"passed_time":23.09291087,"remaining_time":1.500178448},
{"learn":[0.1851736991],"iteration":939,"passed_time":23.11264033,"remaining_time":1.475274915},
{"learn":[0.184951213],"iteration":940,"passed_time":23.13349354,"remaining_time":1.450452836},
{"learn":[0.1848634271],"iteration":941,"passed_time":23.15580655,"remaining_time":1.425729066},
{"learn":[0.1845695665],"iteration":942,"passed_time":23.17593059,"remaining_time":1.400878095},
{"learn":[0.1842566528],"iteration":943,"passed_time":23.19840266,"remaining_time":1.376176429},
{"learn":[0.1838990376],"iteration":944,"passed_time":23.22105889,"remaining_time":1.3514902},
{"learn":[0.1838560412],"iteration":945,"passed_time":23.24499811,"remaining_time":1.326881499},
{"learn":[0.183633387],"iteration":946,"passed_time":23.26930494,"remaining_time":1.302294786},
{"learn":[0.1834747738],"iteration":947,"passed_time":23.29626528,"remaining_time":1.277854214},
{"learn":[0.1834171283],"iteration":948,"passed_time":23.32926299,"remaining_time":1.253732784},
{"learn":[0.1833494524],"iteration":949,"passed_time":23.35966597,"remaining_time":1.229456104},
{"learn":[0.1830303729],"iteration":950,"passed_time":23.38718232,"remaining_time":1.205017806},
{"learn":[0.1829019603],"iteration":951,"passed_time":23.41185913,"remaining_time":1.180429872},
{"learn":[0.1826475412],"iteration":952,"passed_time":23.44310542,"remaining_time":1.156165745},
{"learn":[0.1825802002],"iteration":953,"passed_time":23.47102113,"remaining_time":1.131726386},
{"learn":[0.18255083],"iteration":954,"passed_time":23.50354408,"remaining_time":1.107496841},
{"learn":[0.1822536101],"iteration":955,"passed_time":23.52828013,"remaining_time":1.082891554},
{"learn":[0.182098088],"iteration":956,"passed_time":23.55751,"remaining_time":1.05848791},
{"learn":[0.182006426],"iteration":957,"passed_time":23.58506698,"remaining_time":1.034000849},
{"learn":[0.1819620052],"iteration":958,"passed_time":23.60810933,"remaining_time":1.009314372},
{"learn":[0.1817679477],"iteration":959,"passed_time":23.63151684,"remaining_time":0.9846465351},
{"learn":[0.1814778154],"iteration":960,"passed_time":23.65452578,"remaining_time":0.9599651462},
{"learn":[0.1813654273],"iteration":961,"passed_time":23.67774951,"remaining_time":0.9352957186},
{"learn":[0.18115555],"iteration":962,"passed_time":23.70607347,"remaining_time":0.9108252526},
{"learn":[0.1809411314],"iteration":963,"passed_time":23.7356277,"remaining_time":0.8863927357},
{"learn":[0.1808630887],"iteration":964,"passed_time":23.76283952,"remaining_time":0.861864646},
{"learn":[0.1806598235],"iteration":965,"passed_time":23.78945899,"remaining_time":0.837310151},
{"learn":[0.1804818628],"iteration":966,"passed_time":23.82205407,"remaining_time":0.8129553096},
{"learn":[0.1803917772],"iteration":967,"passed_time":23.85293011,"remaining_time":0.7885266154},
{"learn":[0.1802523933],"iteration":968,"passed_time":23.88565059,"remaining_time":0.7641436205},
{"learn":[0.1800822264],"iteration":969,"passed_time":23.91676503,"remaining_time":0.7396937638},
{"learn":[0.1800495575],"iteration":970,"passed_time":23.95502365,"remaining_time":0.7154435487},
{"learn":[0.1799767029],"iteration":971,"passed_time":23.98461414,"remaining_time":0.6909148105},
{"learn":[0.1797590495],"iteration":972,"passed_time":24.01664227,"remaining_time":0.6664433106},
{"learn":[0.1795414268],"iteration":973,"passed_time":24.04884894,"remaining_time":0.6419610599},
{"learn":[0.179433863],"iteration":974,"passed_time":24.07596032,"remaining_time":0.6173323158},
{"learn":[0.1793332024],"iteration":975,"passed_time":24.10330192,"remaining_time":0.5927041455},
{"learn":[0.1789243496],"iteration":976,"passed_time":24.13452595,"remaining_time":0.5681618187},
{"learn":[0.1788753351],"iteration":977,"passed_time":24.16724894,"remaining_time":0.5436395466},
{"learn":[0.17872347],"iteration":978,"passed_time":24.19509323,"remaining_time":0.5189958711},
{"learn":[0.1784791939],"iteration":979,"passed_time":24.2337097,"remaining_time":0.494565504},
{"learn":[0.1784438093],"iteration":980,"passed_time":24.25880928,"remaining_time":0.4698444203},
{"learn":[0.1783987555],"iteration":981,"passed_time":24.28765361,"remaining_time":0.4451912067},
{"learn":[0.1783555589],"iteration":982,"passed_time":24.31508964,"remaining_time":0.4205051108},
{"learn":[0.1782962891],"iteration":983,"passed_time":24.3393454,"remaining_time":0.3957617138},
{"learn":[0.1780903428],"iteration":984,"passed_time":24.36996538,"remaining_time":0.371116224},
{"learn":[0.1778119261],"iteration":985,"passed_time":24.40043891,"remaining_time":0.3464565363},
{"learn":[0.1776105],"iteration":986,"passed_time":24.42949238,"remaining_time":0.3217663636},
{"learn":[0.1775184611],"iteration":987,"passed_time":24.45198984,"remaining_time":0.2969877308},
{"learn":[0.1774364218],"iteration":988,"passed_time":24.47939248,"remaining_time":0.2722682682},
{"learn":[0.1773911404],"iteration":989,"passed_time":24.5066281,"remaining_time":0.247541698},
{"learn":[0.1771864367],"iteration":990,"passed_time":24.54536403,"remaining_time":0.2229145068},
{"learn":[0.1769479803],"iteration":991,"passed_time":24.57727896,"remaining_time":0.1982038626},
{"learn":[0.1768809472],"iteration":992,"passed_time":24.60363775,"remaining_time":0.173439541},
{"learn":[0.1766227596],"iteration":993,"passed_time":24.63645785,"remaining_time":0.1487110132},
{"learn":[0.1765228314],"iteration":994,"passed_time":24.66680665,"remaining_time":0.1239538023},
{"learn":[0.1763769596],"iteration":995,"passed_time":24.69435133,"remaining_time":0.09917410171},
{"learn":[0.1762429209],"iteration":996,"passed_time":24.71879534,"remaining_time":0.0743795246},
{"learn":[0.175971474],"iteration":997,"passed_time":24.74572474,"remaining_time":0.04959063074},
{"learn":[0.1759048098],"iteration":998,"passed_time":24.77111483,"remaining_time":0.02479591074},
{"learn":[0.175643305],"iteration":999,"passed_time":24.79935275,"remaining_time":0}
]}